Workbook

Sheet Leeme
A1: Matriz de revisión de literatura
A2: Trabajo de grado: Identificación preventiva de información sensible en el uso empresarial de IA generativa mediante un enfoque híbrido de NER y expresiones regulares. Autor: Andrés Felipe Saldarriaga Becerra.
A4: Propósito
A5: Esta matriz documenta la revisión de literatura que sustenta el objetivo específico 1: la taxonomía de información sensible, la asignación de un detector a cada tipo de entidad, las métricas de evaluación y los vacíos que justifican el trabajo. Cada decisión de la tesis que se apoya en la literatura remite a estudios concretos de la hoja Cribado.
A7: Búsqueda
A8: Fuente | B8: Scopus (exportación CSV con 126 registros)
A9: Campos | B9: Título, resumen y palabras clave
A10: Ecuación | B10: TITLE-ABS-KEY(("personally identifiable information" OR PII OR "sensitive information" OR "sensitive data") AND ("named entity recognition" OR NER OR "regular expression*" OR regex) AND (detect* OR anonym* OR de-identif* OR mask* OR redact*) AND (text* OR document* OR prompt*)) AND PUBYEAR > 2021 AND PUBYEAR < 2028
A11: Fecha de la búsqueda replicada | B11: 10 de octubre de 2026
A12: Registros | B12: 126 (dos con año 2027, ya indexados antes de su publicación definitiva)
A14: Resultado del cribado
A15: Decisión | B15: Registros | C15: % del total | D15: Versión anterior
A16: Núcleo | B16: =COUNTIF(Cribado!$H$2:$H$127,A16) -> 85 | C16: =B16/$B$19 -> 0.67460317 | D16: 78
A17: Complementario | B17: =COUNTIF(Cribado!$H$2:$H$127,A17) -> 25 | C17: =B17/$B$19 -> 0.1984127 | D17: 30
A18: Excluido | B18: =COUNTIF(Cribado!$H$2:$H$127,A18) -> 16 | C18: =B18/$B$19 -> 0.12698413 | D18: 18
A19: Total | B19: =SUM(B16:B18) -> 126 | D19: =SUM(D16:D18) -> 126
A20: Decisiones que cambiaron frente a la versión anterior | B20: =SUMPRODUCT(--(Cribado!$H$2:$H$127<>Cribado!$K$2:$K$127)) -> 24
A21: Estudios verificados con el texto completo | B21: =COUNTIF(Cribado!$AQ$2:$AQ$127,"Abstract y texto completo") -> 10
A23: Cómo está organizada
A24: Protocolo | B24: Preguntas de la revisión, criterios de decisión con su código y significado de cada columna de la hoja Cribado.
A25: Cribado | B25: Los 126 registros, uno por fila: decisión, código del criterio, justificación específica y extracción de técnicas, entidades, datos, métricas y rasgos de evaluación. La columna «Decisión en la versión anterior» aparece en rojo cuando la decisión cambió.
A26: Síntesis | B26: Conteos calculados con fórmulas sobre la hoja Cribado: decisiones por criterio y por año, técnicas, entidades, idiomas, dominios y rasgos de evaluación de los estudios núcleo.
A27: Taxonomía | B27: Trazabilidad de las trece etiquetas de la Tabla 6 de la tesis: cuántos estudios núcleo las mencionan, qué estudios respaldan el detector asignado y cuándo la etiqueta se incluye por analogía, sin respaldo directo.
A28: Lectura_profunda | B28: Trece estudios clave revisados más allá del abstract: qué se verificó, sus resultados, la decisión de diseño que sustentan y qué se corrigió frente a lo que decía el abstract.
A29: Hallazgos | B29: Hallazgos de la revisión con su evidencia, su implicación para el diseño y la sección de la tesis donde se usan.
A31: Alcance y limitaciones
A32: • El cribado y la extracción de la hoja Cribado se basan en el título y el abstract de cada registro; una entidad o técnica se marca solo si el abstract la menciona de forma explícita. Por eso las columnas de entidades subestiman lo que los artículos contienen.
A33: • Diez estudios de la hoja Lectura_profunda se verificaron con el texto completo; en S090 y S012 solo se pudo revisar el repositorio y en S048 solo los metadatos. Esa evidencia se reporta aparte y no modifica las marcas basadas en el abstract.
A34: • La revisión la hizo un solo revisor; los criterios explícitos y la justificación de cada decisión permiten que otra persona la repita y la audite.
A35: • Los antecedentes identificados por fuera de Scopus (Chong et al., 2025; Carpentier et al., 2024; Pilán et al., 2022) no forman parte de los 126 registros y se señalan en la hoja Hallazgos.

Sheet Protocolo
A1: Protocolo de la revisión
A3: Preguntas de la revisión
A4: Pregunta | B4: Tema | C4: Pregunta | D4: Hoja donde se responde
A5: P1 | B5: Entidades | C5: ¿Qué tipos de información sensible detectan los trabajos y cómo los organizan? | D5: Taxonomía; Síntesis (entidades)
A6: P2 | B6: Técnicas | C6: ¿Qué técnicas se usan para cada tipo y cuándo combinan reglas con modelos? | D6: Síntesis (técnicas); Taxonomía; Hallazgos
A7: P3 | B7: Datos e idioma | C7: ¿Con qué datos, dominios e idiomas se evalúan, y cuánta evidencia hay en español? | D7: Síntesis (idiomas y dominios)
A8: P4 | B8: Evaluación | C8: ¿Qué métricas usan y cuántos trabajos miden la utilidad del texto protegido o la respuesta de un LLM? | D8: Síntesis (rasgos de evaluación); Hallazgos
A10: Criterios de decisión
A11: Código | B11: Decisión | C11: Se asigna cuando | D11: Ejemplos
A12: N | B12: Núcleo | C12: El estudio detecta, desidentifica, anonimiza, seudonimiza o enmascara información sensible en texto escrito y aporta evidencia sobre entidades, técnicas, datos o métricas. | D12: S026, S039, S090, S107
A13: C1 | B13: Complementario | C13: Privacidad y utilidad, sustitución o generación de datos sintéticos, sin foco en la detección de entidades. | D13: S041, S076, S104
A14: C2 | B14: Complementario | C14: Arquitectura, gobierno o control de acceso de sistemas con LLM, donde la detección es un componente secundario. | D14: S010, S023, S096
A15: C3 | B15: Complementario | C15: La detección se hace sobre texto extraído de imágenes o audio (OCR o reconocimiento de voz); aporta técnicas, pero no el escenario de texto escrito. | D15: S013, S033, S040
A16: C4 | B16: Complementario | C16: Ataques, análisis de riesgo o clasificación de documentos por sensibilidad, sin un mecanismo de protección. | D16: S032, S035, S060
A17: C5 | B17: Complementario | C17: Capítulo, marco general o herramienta amplia sin evaluación de la detección. | D17: S024, S055
A18: E1 | B18: Excluido | C18: No es un estudio primario: fe de erratas o presentación de actas de un congreso. | D18: S006, S092, S114
A19: E2 | B19: Excluido | C19: El problema principal es otro (phishing, vulnerabilidades web, inteligencia de amenazas, predicción judicial, análisis de fraude o de quejas); la privacidad es incidental. | D19: S020, S061, S073
A20: E3 | B20: Excluido | C20: La protección de datos personales es un paso menor de otro proceso y no se evalúa. | D20: S003
A21: El acceso abierto no se usó como criterio de exclusión. Las decisiones se tomaron con el título y el abstract.
A23: Columnas de la hoja Cribado
A24: Columna | B24: Valores | C24: Significado
A25: Decisión y Código | B25: Núcleo, Complementario, Excluido; N, C1–C5, E1–E3 | C25: Decisión del cribado y criterio que la sustenta.
A26: Grupo de dominio | B26: Diez grupos | C26: Agrupa el dominio libre para los conteos de la hoja Síntesis.
A27: Grupo de idioma | B27: Inglés; Español (solo o con otras lenguas); Otra lengua; Multilingüe; No indicado o no aplica | C27: Idioma de los datos evaluados según el abstract.
A28: Técnicas (siete columnas) | B28: X o vacío | C28: Se marca la técnica que el abstract menciona como parte del método o de la comparación.
A29: Híbrido (reglas + modelo) | B29: Sí / No (fórmula) | C29: Sí cuando el estudio combina regex o reglas con un modelo aprendido (ML clásico, transformer o LLM).
A30: Entidades (catorce columnas) | B30: X o vacío | C30: Se marca solo si el abstract nombra ese tipo de dato de forma explícita (por ejemplo, «phone numbers» para PHONE).
A31: Protege el texto antes de enviarlo a un servicio externo | B31: Sí / No | C31: El mecanismo actúa sobre el texto antes de que salga hacia un LLM u otro servicio (proxy, extensión de navegador, filtro previo).
A32: Evalúa la utilidad del texto protegido | B32: Sí / No | C32: Mide preservación semántica, desempeño de una tarea posterior o calidad del texto transformado.
A33: Evalúa la respuesta de un LLM | B33: Sí / No | C33: Mide la respuesta que genera un LLM a partir del texto protegido.
A34: Base de evidencia | B34: Abstract; Abstract y texto completo; Abstract y repositorio | C34: Indica si el estudio también se verificó con el texto completo o, cuando el artículo no estaba disponible, con su repositorio (hoja Lectura_profunda).

Sheet Cribado
A1: ID | B1: Autores | C1: Año | D1: Título | E1: Fuente | F1: Tipo de documento | G1: DOI | H1: Decisión | I1: Código | J1: Justificación (basada en el abstract) | K1: Decisión en la versión anterior | L1: Dominio | M1: Grupo de dominio | N1: Idioma de los datos | O1: Grupo de idioma | P1: Regex / reglas | Q1: Diccionarios / listas | R1: ML clásico o NER no transformer (CRF, BiLSTM, spaCy) | S1: Transformer (BERT y similares) | T1: LLM | U1: Herramienta existente (Presidio, Purview…) | V1: Otra técnica (embeddings, OCR, privacidad diferencial…) | W1: Híbrido (reglas + modelo) | X1: PER | Y1: EMAIL | Z1: PHONE | AA1: ADDRESS | AB1: ID_DOC | AC1: FIN_ID | AD1: DATE | AE1: LOC | AF1: ORG | AG1: CREDENTIAL / SECRET | AH1: NET_DIGITAL | AI1: URL | AJ1: DOC_REF | AK1: Atributo sensible semántico | AL1: Protege el texto antes de enviarlo a un servicio externo | AM1: Evalúa la utilidad del texto protegido | AN1: Evalúa la respuesta de un LLM | AO1: Datos / corpus | AP1: Métricas o resultados del abstract | AQ1: Base de evidencia | AR1: Abstract
A2: S001 | B2: Thakkar M.; Vora J.; Patel K.; Agrawal A.K.; Sorathiya Y. | C2: 2026 | D2: Implementation of an OSINT-Based Dark Web Monitoring Tool for Stolen Personally Identifiable Information (PII) | E2: GSEACT 2026 - 2026 IEEE Global Symposium on Emerging and Communication Technologies | F2: Conference paper | G2: 10.1109/GSEACT68539.2026.11620580 | H2: Núcleo | I2: N | J2: Detecta PII expuesta en texto extraído de la dark web con un motor híbrido de regex, NER y Presidio; útil como evidencia de la combinación con Presidio. | K2: Núcleo | L2: Web / ciberseguridad | M2: Ciberseguridad u otro problema | N2: No indicado | O2: No indicado o no aplica | P2: X | S2: X | U2: X | W2: =IF(AND(P2="X",OR(R2="X",S2="X",T2="X")),"Sí","No") -> Sí | X2: X | AL2: No | AM2: No | AN2: No | AO2: Datos sintéticos | AP2: Exactitud 89,1 % | AQ2: Abstract | AR2: The rise in large-scale data breaches has increased the circulation of stolen Personally Identifiable Information (PII) across anonymized dark web ecosystems, where conventional monitoring tools have limited visibility. Ethical analysis of such environments is further constrained by legal restrictions and the absence of reproducible, open-source research frameworks. This paper presents a hybrid OSINT-based Dark Web Intelligence System designed to ethically detect exposed PII using a multistage pipeline integrating Tor-based anonymous crawling, automated text extraction, and a hybrid detection engine combining Regular Expressions, Named Entity Recognition (NER), and Microsoft Presidio. The system incorporates HMAC-SHA256 hashing for privacy-preserving storage and a modular visualization dashboard for real-time analysis. Evaluation on synthetically generated datasets demonstrated an overall accuracy of 89.1%, outperforming single method approaches by up to 15%. The proposed framework addresses critical gaps in ethical dark web research, offering a scalable, transparent, and academically reproducible approach to early breach detection and cybersecurity threat intelligence. © 2026 IEEE.
A3: S002 | B3: Pulickal E.; Kirtikar Y.; Dalvi T.; Rao A. | C3: 2025 | D3: SquidAct: Automated Custom Redaction | E3: Lecture Notes in Networks and Systems | F3: Conference paper | G3: 10.1007/978-981-96-3361-6_20 | H3: Núcleo | I3: N | J3: Herramienta de redacción de documentos Word y PDF con patrones y NLP, incluidos patrones definidos por el usuario. | K3: Núcleo | L3: Documentos generales | M3: General / documentos | N3: No indicado | O3: No indicado o no aplica | P3: X | R3: X | W3: =IF(AND(P3="X",OR(R3="X",S3="X",T3="X")),"Sí","No") -> Sí | AL3: No | AM3: No | AN3: No | AO3: No indicado | AP3: No reporta métricas cuantitativas | AQ3: Abstract | AR3: There is a critical need for a solution to protect sensitive data in an efficient, easy and automated manner. It is a common practice in various industries to obfuscate documents, however, existing software such as Adobe Acrobat Professional, ObjectiveRedact, and PDF element is either expensive, complex to use, or do not provide sufficient redaction features. The goal of our research is to create an automated redaction tool that can automatically detect and remove sensitive data in Word (.docx) and PDF (.pdf) documents. The tool will utilize pattern recognition algorithms and natural language processing techniques to redact sensitive information including custom user sensitive information. Minimizing the risk of data leakage, saving time, ensuring compliance with regulatory requirements, and allowing users to define their own custom sensitive data patterns to redact are some of the primary objectives of the tool. The tool also offers the users a preview and verification method which allows users to examine and improve redaction suggestions for better accuracy. This feature also promotes keeping the human element in the loop. Robust encryption methods have been put in place to safeguard documents that are being stored. © The Author(s), under exclusive license to Springer Nature Singapore Pte Ltd. 2025.
A4: S003 | B4: Mahammadli E.; Rustamov S. | C4: 2026 | D4: AzText: Curating Web-Scale Pretraining Data for a Low-Resource Language | E4: Communications in Computer and Information Science | F4: Conference paper | G4: 10.1007/978-3-032-31319-5_23 | H4: Excluido | I4: E3 | J4: La redacción de PII con regex es un paso menor de la curación de un corpus; el estudio no evalúa la detección. | K4: Complementario | L4: Corpus de preentrenamiento | M4: General / documentos | N4: Azerí | O4: Otra lengua | P4: X | W4: =IF(AND(P4="X",OR(R4="X",S4="X",T4="X")),"Sí","No") -> No | AL4: No | AM4: No | AN4: No | AO4: CulturaX, OSCAR, C4, Wikipedia | AP4: Perplejidad, exactitud HellaSwag | AQ4: Abstract | AR4: Large language models require large volumes of clean text for pretraining, yet low-resource languages such as Azerbaijani lack curated corpora of sufficient quality and scale. We present a multi-stage curation pipeline for Azerbaijani web text and report a systematic ablation study at n-gram scale. Starting from 14 million documents (4.66 billion tokens) drawn from five sources (CulturaX, OSCAR, C4, Wikipedia, and digitized books), the pipeline applies Unicode normalization, eight heuristic quality filters, ML-based scoring with language identification and n-gram language models (including KenLM), exact and MinHash near-deduplication, and regex-based PII redaction. The final corpus retains 9.5 million documents (3.0 billion tokens), i.e. 67.9% of documents and 64.4% of tokens. For internal comparison of corpus variants, we use n-gram perplexity and a translated Azerbaijani HellaSwag proxy as cheap surrogates; we treat these as screening signals rather than full evaluations of neural pretraining utility. Under this protocol, heuristic filters and deduplication each remove roughly one-sixth of documents. Digitized Azerbaijani books emerge as the most informative single source, and global MinHash deduplication yields a 0.8%-point accuracy gain over no deduplication at 3 billion training tokens. A corpus-trained SentencePiece tokenizer compresses Azerbaijani text 2.7× more efficiently than GPT-2. The contribution is the documented pipeline, the ablation evidence isolating each stage, and the released corpus and tokenizer, which together provide a reproducible starting point for transformer-based Azerbaijani pretraining. All code, the curated corpus, the SentencePiece tokenizer, and the HellaSwag-AZ evaluation set are released publicly. © The Author(s) 2026.
A5: S004 | B5: Pham D.; Kairouz P.; Mireshghallah N.; Bagdasarian E.; Pham C.M.; Houmansadr A. | C5: 2026 | D5: Can Large Language Models Really Recognize Your Name? | E5: ACM FAccT 2026 - Proceedings of the 9th annual ACM Conference on Fairness, Accountability, and Transparency | F5: Conference paper | G5: 10.1145/3805689.3806747 | H5: Núcleo | I5: N | J5: Muestra que los LLM pierden entre 20 % y 40 % de recall en nombres ambiguos; respalda no depender solo de un LLM para PER. | K5: Núcleo | L5: LLM / herramientas de privacidad | M5: LLM / asistentes | N5: Inglés | O5: Inglés | T5: X | W5: =IF(AND(P5="X",OR(R5="X",S5="X",T5="X")),"Sí","No") -> No | X5: X | AL5: No | AM5: No | AN5: No | AO5: AmBench (12.000 nombres ambiguos) | AP5: Recall por tipo de nombre | AQ5: Abstract | AR5: Large language models (LLMs) are increasingly being used in privacy pipelines to detect and remedy sensitive data leakage. These solutions often rely on the premise that LLMs can reliably recognize human names, one of the most important categories of personally identifiable information (PII). In this paper, we reveal how LLMs can consistently mishandle broad classes of human names even in short text snippets due to ambiguous linguistic cues in the contexts. We construct AmBench, a benchmark of over 12,000 real yet ambiguous human names based on the name regularity bias phenomenon. Each name appears in dozens of concise text snippets that are compatible with multiple entity types. Our experiments with 12 state-of-the-art LLMs show that the recall of AmBench names drops by 20-40% compared to more recognizable names. This uneven privacy protection due to linguistic properties raises important concerns about the fairness of privacy enforcement. When the contexts contain benign prompt injections - instruction-like user texts that can cause LLMs to conflate data with commands - AmBench names can become four times more likely to be ignored in Clio, an LLM-powered enterprise tool used by Anthropic AI to extract supposedly privacy-preserving insights from user conversations with Claude. Our findings showcase blind spots in the performance and fairness of LLM-based privacy solutions and call for a systematic investigation into their privacy failure modes and countermeasures. © 2026 Copyright held by the owner/author(s).
A6: S005 | B6: Mortadi A.; Nazih W.; Eldesouki M.I.; Hifny Y. | C6: 2025 | D6: Intelligent De-Identification of Medical Discharge Summaries Using Hybrid NLP Techniques | E6: ACM Transactions on Asian and Low-Resource Language Information Processing | F6: Article | G6: 10.1145/3724118 | H6: Núcleo | I6: N | J6: Desidentificación híbrida con NER, regex y listas de nombres y direcciones. | K6: Núcleo | L6: Clínico | M6: Salud / clínico | N6: Inglés | O6: Inglés | P6: X | Q6: X | R6: X | W6: =IF(AND(P6="X",OR(R6="X",S6="X",T6="X")),"Sí","No") -> Sí | X6: X | AA6: X | AL6: No | AM6: No | AN6: No | AO6: Resúmenes de alta sintéticos, OntoNotes, CoNLL-2003 | AP6: Desempeño de desidentificación | AQ6: Abstract | AR6: Medical discharge summaries are vital documents in healthcare, often containing Personally Identifiable Information (PII), raising concerns regarding privacy and regulatory compliance. This article proposes a cutting-edge approach that utilizes intelligent data de-identification to address this challenge. This article employs Natural Language Processing (NLP) techniques such as Named Entity Recognition (NER), a hybrid approach that integrates Machine Learning (ML) models, Regular Expressions (REGEX)-based recognizers, and extensive lists of names and addresses. The proposed method focuses on achieving a delicate balance between extracting valuable insights from data and safeguarding sensitive information. The evaluation against benchmarks demonstrates significant improvements in de-identification performance, particularly in discharge summaries. We present findings from our system’s evaluation of synthesized discharge summaries, the OntoNotes dataset, and the CoNLL-2003 dataset, demonstrating its effectiveness in anonymizing diverse medical text sources. © 2025 Copyright held by the owner/author(s).
A7: S006 | B7: Jabbarpour A.; Moulton E.; Kaviani S.; Ghassel S.; Zeng W.; Akbarian R.; Couture A.; Roy A.; Liu R.; Lucinian Y.A.; Hejji N.; AlSulaiman S.; Shirazi F.; Leung E.; Bonsall S.; Arfin S.; Gray B.G.; Klein R. | C7: 2025 | D7: Correction: On the construction of a large-scale database of AI-assisted annotating lung ventilation-perfusion scintigraphy for pulmonary embolism (VQ4PEDB) (Frontiers in Nuclear Medicine, (2025), 5, (1632112), 10.3389/fnume.2025.1632112) | E7: Frontiers in Nuclear Medicine | F7: Erratum | G7: 10.3389/fnume.2025.1671281 | H7: Excluido | I7: E1 | J7: Fe de erratas de otro artículo; no es un estudio. | K7: Excluido | L7: Clínico | M7: Salud / clínico | N7: No aplica | O7: No indicado o no aplica | W7: =IF(AND(P7="X",OR(R7="X",S7="X",T7="X")),"Sí","No") -> No | AL7: No | AM7: No | AN7: No | AO7: - | AP7: - | AQ7: Abstract | AR7: We have incorrectly opined about the performance of a private company's third party software. The performance related to Canadian zip codes as well as other types of data was due to a user error and improper configuration of the tool by the authors. We have made the following edits: A correction has been made to the section “Methods, Anonymization of DICOM files and de-identification of clinical reports, second paragraph”. The correct paragraph reads: “For clinical report texts, we adopted and compounded the effect of the following three independent approaches as a conservative de-identification strategy: (1) Segmed Inc.'s Python-based web server was used to remove PII/PHI from clinical reports, (2) RegEx rules were used to remove Canadian formatted addresses and postal codes in Python, and (3) resulting texts were fed to a Microsoft Copilot agent that was instructed to list suspected people names, addresses, street names, 5–8 digit numbers, business names, clinic names and occupations. The agent was further prompted to ignore medical terms. The resulting terms were then manually screened for relevance, the terms were searched for in the text and then replaced with “[Anon]”.” A correction has been made to the section “Discussion, Data Ingestion, first paragraph”. The correct paragraph reads: “QA revealed our unstructured text data to be properly de-identified, highlighting the effectiveness of our multiple layers of de-identification approaches. Structured DICOM data from hospital sources proved straightforward to robustly de-identify using our strategy. Also, during our QA process, various non-structured DICOM tags, such as series description, used during splitting process were identified and addressed accordingly to preserve integrity of workflow.” Original reference 27 has been removed. The original version of this article has been updated. 2025 Jabbarpour, Moulton, Kaviani, Ghassel, Zeng, Akbarian, Couture, Roy, Liu, Lucinian, Hejji, AlSulaiman, Shirazi, Leung, Bonsall, Arfin, Gray and Klein.
A8: S007 | B8: Mírovský J.; Novotná T.; Hladká B. | C8: 2025 | D8: MasKIT-Anonymization and Pseudonymization of Czech Legal Texts | E8: Jazykovedny Casopis | F8: Article | G8: 10.2478/jazcas-2025-0017 | H8: Núcleo | I8: N | J8: Anonimiza y seudonimiza textos jurídicos con NER externo y reglas sobre el análisis sintáctico. | K8: Núcleo | L8: Legal | M8: Legal / policial | N8: Checo | O8: Otra lengua | P8: X | R8: X | W8: =IF(AND(P8="X",OR(R8="X",S8="X",T8="X")),"Sí","No") -> Sí | AL8: No | AM8: No | AN8: No | AO8: Textos jurídicos | AP8: No reporta métricas en el abstract | AQ8: Abstract | AR8: MasKIT is a command-line tool, an on-line web application and a REST API service for anonymization and pseudonymization of Czech legal texts. Taking a plain text as input (e.g. a letter sent by a legal authority to a citizen), it runs external services for dependency parsing and named entity recognition and then via a rule-based approach identifies and replaces sensitive information in the text. © 2025 Jiří Mírovský et al., published by Slovak Academy of Sciences, Ľudovít Štúr Institute of Linguistics.
A9: S008 | B9: Dinesh M.; Aswin A.S.; Kannimoola J.M. | C9: 2025 | D9: Detection and Redaction of Sensitive Data in Application Logs using LLMs | E9: Proceedings of 5th International Conference on Pervasive Computing and Social Networking, ICPCSN 2025 | F9: Conference paper | G9: 10.1109/ICPCSN65854.2025.11034933 | H9: Núcleo | I9: N | J9: LLM ajustado para NER de datos sensibles en logs; argumenta los falsos positivos de las regex en formatos variables. | K9: Núcleo | L9: Software / logs | M9: Software / secretos técnicos | N9: No indicado | O9: No indicado o no aplica | T9: X | W9: =IF(AND(P9="X",OR(R9="X",S9="X",T9="X")),"Sí","No") -> No | AL9: No | AM9: No | AN9: No | AO9: Logs de aplicaciones | AP9: No reporta métricas en el abstract | AQ9: Abstract | AR9: Any public organization that collects or processes client or user data is legally required to protect this information, ensuring that it is not retained, shared, or stored anywhere as plain text. Logs, which aggregate data from multiple systems and services that an organization uses, can unintentionally include sensitive information. Conventional rule-based approaches and regular expressions (regex) to extract Personally Identifiable Information from logs can sometimes be inefficient. They cannot be easily adapted to varying log formats and face high false positives. This work proposes a system using a Large Language Model fine tuned for Named Entity Recognition task to identify sensitive items in logs coupled with a redaction module that encrypts the identified entities to generate tokens that can be used to replace the sensitive data. This system can reduce false positives, be adapted to varying log formats and is more secure thus ensuring privacy without compromising practicality. © 2025 IEEE.
A10: S009 | B10: Kvasnica P. | C10: 2025 | D10: Unstructured documents processing through their anonymization | E10: Journal of Electrical Engineering | F10: Article | G10: 10.2478/jee-2025-0028 | H10: Núcleo | I10: N | J10: Anonimización de decisiones judiciales con NER estadístico, diccionarios y reglas. | K10: Núcleo | L10: Legal | M10: Legal / policial | N10: Eslovaco | O10: Otra lengua | P10: X | Q10: X | R10: X | W10: =IF(AND(P10="X",OR(R10="X",S10="X",T10="X")),"Sí","No") -> Sí | AL10: No | AM10: No | AN10: No | AO10: Decisiones judiciales anotadas | AP10: No reporta métricas en el abstract | AQ10: Abstract | AR10: In Slovakia, a large number of texts on decisions are published by the courts on the MSSR website. All decisions that are published must be anonymous, without all personal and other data (personal and sensitive data that can identify individual entities in the proceedings, reveal their private data, etc.) to the extent described by the decree. Anonymization of court decision data is carried out according to an instruction given in the Court Management application, which supports only basic anonymization functions. Such an anonymization method is time- and human-resource-intensive, and at the same time, it is susceptible to the leakage of sensitive data. The text processing is based on machine learning methods using the principles of user-friendly visualization to accelerate anonymization and minimize the risk of leaking sensitive data. Achieving and improving results in practice the method of recognizing named entities based on the processing of text documents, dictionaries, rules and a trained statistical model on manually annotated data is used. The article describes the basic techniques of the anonymization used in practice, that are machine learning and removing information. Our attention is given to text documents processing, tools and principles for creating a data set of annotated data and evaluating the success of anonymization. The iteratively improving learning model is dominant in that it enables the use of knowledge as well as annotated data. © 2025 Peter Kvasnica, published by Sciendo.
A11: S010 | B11: Li Y.; Li C.; Wang Z.; Sui D.; Yan J. | C11: 2025 | D11: A Privacy-Preserving Framework for Medical Chatbot Based on LLM with Retrieval Augmented Generation | E11: Lecture Notes in Computer Science (including subseries Lecture Notes in Artificial Intelligence and Lecture Notes in Bioinformatics) | F11: Conference paper | G11: 10.1007/978-981-97-9437-9_2 | H11: Complementario | I11: C2 | J11: Marco de privacidad para un chatbot médico con RAG; el NER que anonimiza PII es un componente entre varios. | K11: Complementario | L11: Clínico / LLM | M11: LLM / asistentes | N11: No indicado | O11: No indicado o no aplica | R11: X | T11: X | W11: =IF(AND(P11="X",OR(R11="X",S11="X",T11="X")),"Sí","No") -> No | AL11: No | AM11: No | AN11: No | AO11: Base de conocimiento médica | AP11: No reporta métricas en el abstract | AQ11: Abstract | AR11: With the continuous advancement of Large Language Models (LLMs) and generative AI technologies, an increasing number of organizations are customizing and fine-tuning LLMs with internal data and documents to enhance the efficiency and reliability of data-driven decision-making. However, these approaches also present challenges in terms of data privacy, protection, and governance. In this paper, we investigate the implementation of privacy preservation in the construction of medical Knowledge Base Question Answering (KBQA) based on LLMs. We propose a solution involving fine-grained access control, the de-identification of sensitive data, and prompt engineering with Chain of Thought (CoT). Specifically, the visibility of information is determined based on user identity, and named entity recognition is employed to anonymize personally identifiable information. We also incorporate prompt engineering with Chain of Thought (CoT) to further enhance data privacy. Experimental study has demonstrated the effectiveness of our privacy protection framework. © The Author(s), under exclusive license to Springer Nature Singapore Pte Ltd. 2025.
A12: S011 | B12: Anselmo M.; Ribas B.C. | C12: 2025 | D12: Pseudonymization in Legal Texts According to the LGPD: A Named Entity Recognition Approach | E12: Lecture Notes in Computer Science (including subseries Lecture Notes in Artificial Intelligence and Lecture Notes in Bioinformatics) | F12: Conference paper | G12: 10.1007/978-3-031-79032-4_22 | H12: Núcleo | I12: N | J12: Transformer más regex para seudonimizar textos jurídicos según la LGPD, con datos sintéticos generados por LLM. | K12: Núcleo | L12: Legal | M12: Legal / policial | N12: Portugués | O12: Otra lengua | P12: X | S12: X | T12: X | W12: =IF(AND(P12="X",OR(R12="X",S12="X",T12="X")),"Sí","No") -> Sí | AL12: No | AM12: No | AN12: No | AO12: LeNER-Br y datos sintéticos de Llama 3 | AP12: No reporta valores en el abstract | AQ12: Abstract | AR12: This study explores the application of Named Entity Recognition (NER) for the pseudonymization of data in legal texts, aiming to protect Personally Identifiable Information (PII) in compliance with Brazil’s General Data Protection Law (LGPD). The research highlights the challenge of balancing data privacy and utility, presenting a methodology that uses artificial intelligence technologies to effectively identify and obscure PII in legal documents. In this study, we propose a Transformer model along with Regex techniques to identify entities in a text. To test the model, we created a new dataset from the existing LenerBR. We also used a function and prompt engineering applied to the Llama 8B version 3 model to generate synthetic data. Tests showed the need for further adjustments in the proposed new model. Future work will focus on improving the model’s accuracy and efficiency, as well as enhancing the identification of sensitive data and learning from user interactions. © The Author(s), under exclusive license to Springer Nature Switzerland AG 2025.
A13: S012 | B13: Le K.T.; Gärtner L.; Fleischle F.; Schöller T.; Große S.; Ulusoy I. | C13: 2026 | D13: mailcom: Pseudonymization tool for textual data | E13: SoftwareX | F13: Article | G13: 10.1016/j.softx.2026.102703 | H13: Núcleo | I13: N | J13: Paquete abierto de seudonimización (mailcom) como capa previa a la revisión humana. | K13: Núcleo | L13: Correos / humanidades digitales | M13: Software / secretos técnicos | N13: Multilingüe | O13: Multilingüe | R13: X | W13: =IF(AND(P13="X",OR(R13="X",S13="X",T13="X")),"Sí","No") -> No | AL13: No | AM13: No | AN13: No | AO13: No indicado | AP13: No reporta métricas en el abstract | AQ13: Abstract y documentación del repositorio (texto completo no disponible) | AR13: The rapid growth of data and its use has heightened concerns about data privacy. To support research on data that contains sensitive attributes, we developed the mailcom package for pseudonymization. mailcom is built entirely on open-source libraries and is designed for configurability and extensibility. Several languages are supported by default, with the option to add additional languages. Since pseudonymized outputs still require human review to guarantee full anonymization, the package serves as a scalable pre-processing layer that reduces manual work while establishing a principled baseline of privacy protection, enabling reproducible research on digital text under current data-ethics and governance standards. © 2026 The Author(s).
A14: S013 | B14: Parra Ariza A.J.; Rueda-Chacón H. | C14: 2026 | D14: Preserving Identity in Speech: Anonymized Transcription for the Colombian Context; [Preservando la Identidad en el Habla: Transcripción Anonimizada para el Contexto Colombiano] | E14: Procesamiento del Lenguaje Natural | F14: Article | G14: 10.26342/2026-76-16 | H14: Complementario | I14: C3 | J14: Anonimiza transcripciones de voz en español colombiano; es la única evidencia colombiana, pero el texto proviene de audio. | K14: Complementario | L14: Voz / transcripción | M14: Voz o imagen | N14: Español (Colombia) | O14: Español (solo o con otras lenguas) | R14: X | S14: X | W14: =IF(AND(P14="X",OR(R14="X",S14="X",T14="X")),"Sí","No") -> No | X14: X | AB14: X | AL14: No | AM14: No | AN14: No | AO14: Corpus de habla colombiano | AP14: WER 7,60 %; F1 NER 60,81 %; F1 anonimización 76,10 % | AQ14: Abstract | AR14: Speech has driven the development of Automatic Speech Recognition (ASR) models like Whisper, capable of converting spoken language into written text. However, these models require large amounts of data (corpora), which limits their performance in languages or variants with scarce resources, such as the Colombian Spanish, whose accents and regionalisms are underrepresented. Likewise, the use of recordings often includes sensitive information, such as names or IDs, which makes the collection and sharing of these corpora difficult. This work proposes the development of a model based on the Whisper arquitecture and WhisperX’s pipeline, for anonymized speech transcription in Colombian Spanish, with temporal annotation and speaker diarization. With models achieving a 7,60 % transcription word error rate (WER), an F1-score of 60,81 % for named entity recognition, and an F1-score of 76,10 % for anonymization, it contributes to closing the gap between existing models and Colombian dialects, ensuring robust performance even in low-resource settings. © 2026 Sociedad Española para el Procesamiento del Lenguaje Natural
A15: S014 | B15: Hassan F.; Sanchez D.; Domingo-Ferrer J. | C15: 2023 | D15: Utility-Preserving Privacy Protection of Textual Documents via Word Embeddings | E15: IEEE Transactions on Knowledge and Data Engineering | F15: Article | G15: 10.1109/TKDE.2021.3076632 | H15: Núcleo | I15: N | J15: Detecta términos reveladores con embeddings en vez de un conjunto fijo de entidades y reemplaza por generalizaciones; muestra el límite de las etiquetas fijas. | K15: Complementario | L15: Documentos generales | M15: General / documentos | N15: Inglés | O15: Inglés | V15: X | W15: =IF(AND(P15="X",OR(R15="X",S15="X",T15="X")),"Sí","No") -> No | AL15: No | AM15: Sí | AN15: No | AO15: Colecciones de documentos | AP15: Protección y utilidad frente a NER | AQ15: Abstract | AR15: Text is the most usual way to share information in society. Yet, if textual documents contain personal sensitive information, they cannot be shared with third parties or released publicly without adequate protection. Privacy-preserving mechanisms provide ways to sanitize data so that identities and/or confidential attributes are not disclosed. In the last twenty years, a great variety of mechanisms have been proposed to protect structured databases with numerical and categorical attributes; however, little attention has been devoted to unstructured textual data. In general, textual data protection requires first detecting pieces of text that may lead to disclosure of sensitive information and then masking those pieces via suppression or generalization. Current solutions rely on pre-trained classifiers that can recognize a fixed set of (allegedly disclosive) named entities, such as names or locations. Yet, such approaches fall short of providing adequate protection because in reality disclosive information is not limited to a predefined set of entity types, and not all the appearances of certain entity type result in disclosure. Besides, named entity recognition requires considerable manual effort to tag the training data needed to build classifiers. In this work we propose a more general and flexible solution for textual data protection. By means of word embeddings we build vectors that numerically capture the semantic relationships of the textual terms appearing in a collection of documents. Then we evaluate the disclosure caused by the textual terms on the entity to be protected (e.g., an individual's identity or a confidential attribute) according to the similarity between their vector representations. Our method also limits the semantic loss (and, therefore, the utility loss) of the document by replacing (rather than just suppressing) disclosive terms with privacy-preserving generalizations. Empirical results show that our approach offers much more robust protection and greater utility preservation than methods based on named entity recognition, with the additional important advantage of avoiding the burden of manual data tagging. © 1989-2012 IEEE.
A16: S015 | B16: Shettennavar S.B.; Sharma S.; Aswathy J.S.; Rakshitha K.S.; Karthika R. | C16: 2026 | D16: Offline Photo-Shield Automatic System for Finding and Redacting Privacy-Sensitive Information in Images | E16: Proceedings of the 6th International Conference on Pervasive Computing and Social Networking, ICPCSN 2026 | F16: Conference paper | G16: 10.1109/ICPCSN68523.2026.11543660 | H16: Complementario | I16: C3 | J16: Redacción en imágenes con OCR y regex, con puntaje de riesgo; aporta tipos de identificador pero la entrada no es texto. | K16: Excluido | L16: Imágenes | M16: Voz o imagen | N16: No indicado | O16: No indicado o no aplica | P16: X | V16: X | W16: =IF(AND(P16="X",OR(R16="X",S16="X",T16="X")),"Sí","No") -> No | Y16: X | Z16: X | AA16: X | AB16: X | AC16: X | AD16: X | AL16: No | AM16: No | AN16: No | AO16: Imágenes | AP16: Exactitud | AQ16: Abstract | AR16: The Photo-shield Automatic System presents a fully offline, AI-driven image redaction system for protecting sensitive information in digital images. This system automatically detects faces and text using EasyOCR and Media Pipe, respectively. The extracted text is analyzed using Python-based classifiers and REGEX techniques to identify privacy-critical entities. It recognizes Aadhaar, PAN numbers, phone numbers, email IDs, addresses, date of birth, financial details and vehicle registration plates. The detected faces and sensitive text regions are classified into predefined categories. Appropriate masking techniques, such as Gaussian blur or blackout are applied using OpenCV. This entire pipeline operates offline, ensuring data security and eliminating cloud dependency. A predefined risk-scoring module is used to evaluate the severity of privacy for each image. An automated PDF report of risk analysis summarizes the detected and redacted regions. The experimental results show high accuracy across multiple images and environment contexts. © 2026 IEEE.
A17: S016 | B17: Yao Z.; Hong K.; Wang X.; Ma J. | C17: 2026 | D17: Automatic Anonymization of Unstructured Text: Detecting Sensitive Information with Fine-Tuning Large Language Models | E17: 2026 4th International Conference on Big Data and Privacy Computing, BDPC 2026 | F17: Conference paper | G17: 10.1109/BDPC69980.2026.11608232 | H17: Núcleo | I17: N | J17: Compara LLM ajustados (Prefix Tuning y LoRA) con NER y reglas para anonimizar texto. | K17: Núcleo | L17: Texto no estructurado | M17: General / documentos | N17: No indicado | O17: No indicado o no aplica | P17: X | R17: X | T17: X | W17: =IF(AND(P17="X",OR(R17="X",S17="X",T17="X")),"Sí","No") -> Sí | AL17: No | AM17: No | AN17: No | AO17: No indicado | AP17: Desempeño de anonimización | AQ17: Abstract | AR17: In the age of digital connectivity, vast amounts of data are openly shared across social platforms, e-commerce platforms, and other online channels, potentially leading to inadvertent exposure of sensitive information. As a crucial mechanism for protecting sensitive information, anonymization techniques for structured data have already reached a relatively mature stage. Nevertheless, unstructured textual data lacks fixed structures and involves diverse entity types, making sensitive information difficult to identify through automated methods. Meanwhile, automated anonymization of unstructured text still relies heavily on manual processing, which is costly and inefficient, and thus requires further optimization. Presently, Large Language Models (LLMs) have demonstrated remarkable capabilities in semantic understanding and reasoning, but its effectiveness in anonymizing sensitive information within unstructured text still lacks systematic research. In this paper, we employ two fine-tuning approaches, namely Prefix Tuning and Low-Rank Adaptation (LoRA) Fine-Tuning, and verify that fine-tuned LLMs still achieve excellent performance in the task of anonymizing sensitive information in texts. Furthermore, we conduct a comparative evaluation and analyze their similarities and differences with traditional Named Entity Recognition (NER) and rule-based anonymization approaches. The evaluation results indicate that the fine-tuning model achieves outstanding performance in sensitive information anonymization tasks. © 2026 IEEE.
A18: S017 | B18: Albanese F.; Ronco P.; D'Ippolito N. | C18: 2026 | D18: Anonymous-by-Construction: An LLM-Driven Framework for Privacy-Preserving Text | E18: Proceedings - 2026 International Workshop on Responsible AI Engineering, RAIE 2026 | F18: Conference paper | G18: 10.1145/3786156.3788578 | H18: Núcleo | I18: N | J18: Sustitución local de PII antes de un LLM, comparada con Presidio y Google DLP; evalúa la calidad de las respuestas del agente. | K18: Núcleo | L18: Conversaciones / LLM | M18: LLM / asistentes | N18: Inglés | O18: Inglés | T18: X | U18: X | W18: =IF(AND(P18="X",OR(R18="X",S18="X",T18="X")),"Sí","No") -> No | X18: X | AL18: Sí | AM18: Sí | AN18: Sí | AO18: Action-Based Conversation Dataset | AP18: Recall de PII, utilidad semántica, calidad de respuestas del agente | AQ18: Abstract y texto completo | AR18: Responsible use of AI demands that we protect sensitive information without undermining the usefulness of data, an imperative that has become acute in the age of large language models. We address this challenge with an on-premise, LLM-driven substitution pipeline that anonymizes text by replacing personally identifiable information (PII) with realistic, type-consistent surrogates. Executed entirely within organizational boundaries using local LLMs, the approach prevents data egress while preserving fluency and task-relevant semantics.We conduct a systematic, multi-metric, cross-Technique evaluation on the Action-Based Conversation Dataset, benchmarking against industry standards (Microsoft Presidio and Google DLP) and a state-of-The-Art approach (ZSTS, in redaction-only and redaction-plus-substitution variants). Our protocol jointly measures privacy (PII recall), semantic utility (sentiment agreement, topic distance), and trainability under privacy via a lifecycle-ready criterion obtained by fine-Tuning a compact encoder (BERT+LoRA) on sanitized text. In addition, we assess agentic Q&A performance by inserting an on-premise anonymization layer before the answering LLM and evaluating the quality of its responses. This intermediate, type-preserving substitution stage ensures that no sensitive content is exposed to third-party APIs, enabling responsible deployment of Q&A agents without compromising confidentiality.Our method attains state-of-The-Art privacy, minimal topical drift, strong factual utility, and low trainability loss, outperforming rule-based approaches and named-entity recognition (NER) baselines and ZSTS variants on the combined privacy-utility-Trainability frontier. These results show that local LLM substitution yields anonymized corpora that are both responsible to use and operationally valuable: safe for agentic pipelines over conversational data and suitable for downstream fine-Tuning with limited degradation. By coupling on-premise anonymization with rigorous, auditable evaluation, this work offers decision-ready evidence for deploying Responsible-AI-by-Design systems in real-world settings. © 2026 Copyright held by the owner/author(s).
A19: S018 | B19: Berzi A.; Berényi E.; Képes Z.; Antal B.; Varga Á.G.; Emri M. | C19: 2025 | D19: NLP-based removal of personally identifiable information from Hungarian electronic health records | E19: Frontiers in Artificial Intelligence | F19: Article | G19: 10.3389/frai.2025.1585260 | H19: Núcleo | I19: N | J19: Modelos spaCy para PII en historias clínicas, con pre-anotación por reglas; muestra el uso de pre-anotación. | K19: Núcleo | L19: Clínico | M19: Salud / clínico | N19: Húngaro | O19: Otra lengua | P19: X | R19: X | W19: =IF(AND(P19="X",OR(R19="X",S19="X",T19="X")),"Sí","No") -> Sí | AL19: No | AM19: No | AN19: No | AO19: 15.000 historias clínicas, 90.000 PII | AP19: F1 0,970–0,993; 99,67 % de PII removida | AQ19: Abstract | AR19: Introduction: Electronic health records (EHR) in text format serve as crucial resources for data-driven medical research. To safeguard patient confidentiality, under the General Data Protection Regulation (GDPR), strict measures are required to ensure personal data is anonymized or pseudonymized to protect individual privacy. Natural language processing has consistently proven effective in automating the de-identification of sensitive information. Methods: We present spaCy models to recognize personally identifiable information (PII) from a wide range of free-text medical records written in Hungarian, a low-resource language. To develop this model, we compiled a corpus of clinical documents by annotating sensitive information within electronic health records sourced from the University of Debrecen. To simplify the annotation process, we pre-annotated the documents using a rule-based method. The corpora comprises over 15,000 documents and includes more than 90,000 instances of PII. We trained several models using this corpus and also developed a separate validation corpus to assess their performance. Results: The performance evaluation of the de-identification models on the developed corpora resulted in F1-scores ranging from 0.9697 to 0.9926. On the validation corpora, the F1-scores ranged from 0.9772 to 0.9867, demonstrating that the models can effectively handle previously unseen examples. Our risk analysis revealed that 99.67% of the sensitive information was successfully removed from the validation dataset. Discussion: The results indicate that similarly to other state-of-the-art systems our model is highly effective at identifying PII in clinical texts, guaranteeing that sensitive information in clinical documents can be protected without sacrificing the quality or usability of the data for research purposes. Despite these positive outcomes, several areas remain to be improved, such as the conduction of additional testing on diverse datasets, particularly those from different healthcare institutions. With ongoing refinements, these models have the potential to greatly enhance the efficiency of data de-identification processes, ensuring compliance with privacy regulations while promoting the secure sharing of medical data for scientific progress. Copyright © 2025 Berzi, Berényi, Képes, Antal, Varga and Emri.
A20: S019 | B20: Ren L.; Belkadi S.; Han L.; Del-Pinto W.; Nenadic G. | C20: 2025 | D20: Synthetic4Health: generating annotated synthetic clinical letters | E20: Frontiers in Digital Health | F20: Article | G20: 10.3389/fdgth.2025.1497130 | H20: Complementario | I20: C1 | J20: Genera cartas clínicas sintéticas desidentificadas; aporta a la generación de datos sintéticos, no a la detección. | K20: Complementario | L20: Clínico | M20: Salud / clínico | N20: Inglés | O20: Inglés | S20: X | T20: X | W20: =IF(AND(P20="X",OR(R20="X",S20="X",T20="X")),"Sí","No") -> No | AL20: No | AM20: Sí | AN20: No | AO20: Cartas clínicas | AP20: BERTScore y NER aguas abajo | AQ20: Abstract | AR20: Clinical letters contain sensitive information, limiting their use in model training, medical research, and education. This study aims to generate reliable, diverse, and de-identified synthetic clinical letters to support these tasks. We investigated multiple pre-trained language models for text masking and generation, focusing on Bio_ClinicalBERT, and applied different masking strategies. Evaluation included qualitative and quantitative assessments, downstream named entity recognition (NER) tasks, and clinically focused evaluations using BioGPT and GPT-3.5-turbo. The experiments show: (1) encoder-only models perform better than encoder–decoder models; (2) models trained on general corpora perform comparably to clinical-domain models if clinical entities are preserved; (3) preserving clinical entities and document structure aligns with the task objectives; (4) Masking strategies have a noticeable impact on the quality of synthetic clinical letters: masking stopwords has a positive impact, while masking nouns or verbs has a negative effect; (5) The BERTScore should be the primary quantitative evaluation metric, with other metrics serving as supplementary references; (6) Contextual information has only a limited effect on the models' understanding, suggesting that synthetic letters can effectively substitute real ones in downstream NER tasks; (7) Although the model occasionally generates hallucinated content, it appears to have little effect on overall clinical performance. Unlike previous research, which primarily focuses on reconstructing original letters by training language models, this paper provides a foundational framework for generating diverse, de-identified clinical letters. It offers a direction for utilizing the model to process real-world clinical letters, thereby helping to expand datasets in the clinical domain. Our codes and trained models are available at https://github.com/HECTA-UoM/Synthetic4Health. 2025 Ren, Belkadi, Han, Del-Pinto and Nenadic.
A21: S020 | B21: Arthy S.; Sakthi Priya G. | C21: 2025 | D21: A Hybrid Machine Learning Approach for Securing Emails:Phishing Detection and Prevention | E21: 2025 3rd International Conference on Advancements in Electrical, Electronics, Communication, Computing and Automation, ICAECA 2025 | F21: Conference paper | G21: 10.1109/ICAECA63854.2025.11012305 | H21: Excluido | I21: E2 | J21: El problema es la detección de phishing; el NER se usa para validar entidades del correo. | K21: Excluido | L21: Correo / phishing | M21: Ciberseguridad u otro problema | N21: No indicado | O21: No indicado o no aplica | P21: X | R21: X | S21: X | W21: =IF(AND(P21="X",OR(R21="X",S21="X",T21="X")),"Sí","No") -> Sí | AL21: No | AM21: No | AN21: No | AO21: Correos | AP21: Exactitud de detección de phishing | AQ21: Abstract | AR21: Email phishing is a cyberattack in which an attacker sends fraudulent emails that appear to be from legitimate sources. The intension of phishing attack is to deceive the recipient into disclosing sensitive information, such as passwords, credit card numbers, or personal information, or into clicking on malicious links or downloading malware. These emails frequently employ social engineering tactics to infuse a sense of urgency or fear in users, prompting them to take immediate action without verifying the message's authenticity. Phishing attacks continue to be a major security threat in email communication, necessitating advanced methods for detection. This paper introduces an innovative phishing detection email extension that integrates Neuro-Symbolic AI, Dynamic Contextual Analysis (DCA), and Memory-Augmented Neural Networks (MANNs) to effectively identify and block phishing attempts in real-time. The extension leverages a Neuro-Symbolic Hybrid Model(NSHM) that combines rule-based reasoning with deep learning to analyse email content and flag suspicious elements. Dynamic Contextual Analysis enhances the detection by evaluating sender behavior, metadata, and email timing to spot anomalies in email interactions. Additionally, Memory-Augmented Neural Networks allow the system to retain knowledge of past phishing patterns, enabling it to adapt to emerging and sophisticated phishing strategies. The email extension incorporates Named Entity Recognition (NER) to detect and validate key entities (such as organizations, URLs), and Domain Reputation Analysis to assess the legitimacy of links embedded in emails. To ensure transparency and user trust, explainability techniques like LIME (Local Interpretable Model-Agnostic Explanations) and SHAP (SHapley Additive exPlanations) are integrated, providing users with insights into why an email is classified as phishing. Experimental results show that this extension significantly improves phishing detection accuracy, reduces false positives, and provides an intuitive and secure user experience for real-time email protection. © 2025 IEEE.
A22: S021 | B22: Dai J.; Li H. | C22: 2026 | D22: Pixel-Level Privacy Preserving in DICOM Anonymisation | E22: Lecture Notes of the Institute for Computer Sciences, Social-Informatics and Telecommunications Engineering, LNICST | F22: Conference paper | G22: 10.1007/978-3-032-14350-1_14 | H22: Complementario | I22: C3 | J22: Anonimización de DICOM con OCR y NER; la entrada es imagen. | K22: Excluido | L22: Imágenes médicas | M22: Voz o imagen | N22: No indicado | O22: No indicado o no aplica | R22: X | V22: X | W22: =IF(AND(P22="X",OR(R22="X",S22="X",T22="X")),"Sí","No") -> No | AL22: No | AM22: No | AN22: No | AO22: Archivos DICOM | AP22: No reporta métricas en el abstract | AQ22: Abstract | AR22: DICOM (Digital Imaging and Communications in Medicine) is a standard format for medical images, often containing sensitive patient information. To protect patient privacy, anonymizing DICOM files before sharing or storage is essential, this work introduces a novel DICOM medical image anonymization approach that employs Optical Character Recognition (OCR) to identify personally identifiable information (PII) within both tags and textual content embedded within images. By employing Named Entity Recognition (NER) techniques, the system accurately detects PII in textual data. The proposed method operates independently of metadata, enabling the anonymization of sensitive information in both tags and pixel-level image content. This approach can help efficient and automated anonymization of medical image files, significantly enhancing patient privacy. © ICST Institute for Computer Sciences, Social Informatics and Telecommunications Engineering 2026.
A23: S022 | B23: Asiri S.; Alshehri R.; Kamran F.; Laznam H.; Xiao Y.; Alzahrani S. | C23: 2025 | D23: SPADR: A Context-Aware Pipeline for Privacy Risk Detection in Text Data | E23: Electronics (Switzerland) | F23: Article | G23: 10.3390/electronics14183725 | H23: Núcleo | I23: N | J23: Detecta riesgos explícitos y contextuales en correos con NER, autoencoder y grafos; fuente de la métrica de fuga residual. | K23: Núcleo | L23: Correo corporativo | M23: Empresarial | N23: Inglés | O23: Inglés | R23: X | V23: X | W23: =IF(AND(P23="X",OR(R23="X",S23="X",T23="X")),"Sí","No") -> No | AL23: Sí | AM23: Sí | AN23: No | AO23: Enron Email Dataset | AP23: Fuga residual de 100 % a 16,06 %; BERTScore F1 88,03 % | AQ23: Abstract y texto completo | AR23: Large language models (LLMs) are powerful, but they can unintentionally memorize and leak sensitive information found in their training or input data. To address this issue, we propose SPADR, a semantic privacy anomaly detection and remediation pipeline designed to detect and remove privacy risks from text. SPADR addresses limitations in existing redaction methods by identifying deeper forms of sensitive content, including implied relationships, contextual clues, and non-standard identifiers that traditional NER systems often overlook. SPADR combines semantic anomaly scoring using a denoising autoencoder with named entity recognition and graph-based analysis to detect both direct and hidden privacy risks. It is flexible enough to work on both training data (to prevent memorization) and user input (to prevent leakage at inference time). We evaluate SPADR on the Enron Email Dataset, where it significantly reduces document-level privacy leakage while maintaining strong semantic utility. The enhanced version, SPADR (S2), reduces the PII leak rate from 100% to 16.06% and achieves a BERTScore F1 of 88.03%. Compared to standard NER-based redaction systems, SPADR offers more accurate and context-aware privacy protection. This work highlights the importance of semantic and structural understanding in building safer, privacy-respecting AI systems. © 2025 by the authors.
A24: S023 | B24: Gundaboina A.; Choudhry M.; Ramuloo V.A.S.; Banakar S.; Kumar A. | C24: 2026 | D24: An AI-Driven Privacy-Preserving Framework for Automated Legal Hold, Data Preservation, and Enterprise Data Compliance | E24: Journal of Intelligent Decision Making and Information Science | F24: Article | G24: 10.59543/jidmis.v3.2085 | H24: Complementario | I24: C2 | J24: Retención legal en empresas con NER y privacidad diferencial; señalar datos sensibles es una función secundaria. | K24: Complementario | L24: Empresarial / cumplimiento | M24: Empresarial | N24: No indicado | O24: No indicado o no aplica | R24: X | S24: X | V24: X | W24: =IF(AND(P24="X",OR(R24="X",S24="X",T24="X")),"Sí","No") -> No | AL24: No | AM24: No | AN24: No | AO24: Corpus empresarial de correos y documentos | AP24: Exactitud 92,40 %; F1 91,59 % | AQ24: Abstract | AR24: Identifying, preserving and governing electronically stored information (ESI) is a huge challenge for enterprise organizations in terms of legal-hold requirements, privacy regulations and data retention requirements. Compliance mechanisms currently in place are mostly based on manual review and pre-defined rules which delay preservation, lack consistency in legal relevance assessment, cause privacy exposure and raise overhead to the operations. The purpose of this research is to create an AI-based privacy preserving approach to automated legal hold, intelligent data preservation and enterprise compliance management. The proposed methodology enhances the existing methodology with a Privacy-Aware Legal Hold Intelligence (PALHI) algorithm that consists of concepts from transformer-based semantic classification, named-entity recognition, risk-aware policy reasoning, federated learning, and differential privacy. PALHI can be used to identify records that are relevant to litigation, to flag sensitive data, to prioritize records for preservation and to ensure the policy matches the context of the data. Experimental results show that performance, measured by the accuracy, precision, recall, F1-score and legal-hold detection rate, on a benchmark enterprise email and document corpus is 92.40%, 91.86%, 91.32%, 91.59% and 93.18%, respectively, with only 6.42% of false preservation decisions. The accuracy loss due to differential privacy (DP) at the level of ε=1.0 is only 2.16%. The novelty of the framework is that it is able to fuse together the concepts of relevance detection, distributed privacy preservation, and automated compliance reasoning at the same time, and do so in an intelligent manner. It provides an auditable, scalable way that decreases the compliance effort needed to do it manually and increases the reliability of preservation, confidentiality and responsiveness to regulatory requests.
A25: S024 | B25: Kumar A. | C25: 2026 | D25: Designing Guardrails: Ensuring Responsible AI Behavior | E25: GenAI and LLMs for Beyond 5G Networks | F25: Book chapter | G25: 10.1007/978-3-032-06418-9_5 | H25: Complementario | I25: C5 | J25: Capítulo sobre guardrails para IA generativa en empresas; menciona filtros de entrada con regex para evitar fuga de PII. | K25: Complementario | L25: Empresarial / LLM | M25: LLM / asistentes | N25: No aplica | O25: No indicado o no aplica | P25: X | R25: X | W25: =IF(AND(P25="X",OR(R25="X",S25="X",T25="X")),"Sí","No") -> Sí | AL25: Sí | AM25: No | AN25: No | AO25: - | AP25: - | AQ25: Abstract | AR25: As generative AI rapidly integrates into enterprise ecosystems, the need for robust guardrails has become a critical concern for organizations seeking to leverage this powerful technology responsibly. This chapter provides a comprehensive framework for designing, implementing, and governing AI guardrails to ensure safety, fairness, control, and compliance in high-stakes business environments. The chapter begins by contextualizing the urgent need for responsible AI in enterprise settings, emphasizing risks such as hallucinations, bias, and privacy breaches. It highlights how unguarded generative AI systems can not only produce harmful outputs but also expose organizations to regulatory penalties, reputational damage, and operational inefficiencies. With regulations such as the EU Artificial Intelligence Act imposing strict governance requirements on high-risk AI applications, enterprises must adopt proactive measures to maintain compliance and public trust. The core of the chapter explores a multilayered approach to AI guardrails, encompassing technical, procedural, and human oversight mechanisms. At the technical level, input filtering (e.g., regex and ML classifiers), output validation (e.g., schema enforcement, toxicity detectors), and grounding with enterprise knowledge are emphasized as vital components in limiting model misbehavior. Reinforcement Learning from Human Feedback (RLHF) and constitutional AI techniques are explored as strategies to tune models toward ethical and organizational values. Tools such as Guardrails AI, PromptFoo, and Amazon Bedrock Guardrails provide tangible implementation pathways for enterprises. On the procedural side, the chapter outlines governance frameworks—policies, ethics committees, and compliance programs—that define roles and responsibilities across the AI lifecycle. It stresses the importance of policy-as-code to embed these rules into CI/CD workflows, enabling scalable and automated enforcement. A hybrid architecture combining automated enforcement with human-in-the-loop (HITL) mechanisms is advocated to catch edge cases and ensure nuanced decision-making where AI models fall short. Enterprise case studies provide compelling validation of these approaches. Banks have used real-time guardrails to prevent the leakage of personally identifiable information (PII), while healthcare providers rely on schema validators to filter out unsafe medical advice. These examples demonstrate not only reduced risk exposure and improved regulatory compliance but also tangible business value, such as faster audit readiness and enhanced customer trust. A key innovation discussed in the chapter is knowledge grounding through retrieval-augmented generation (RAG), which ties generative outputs to authoritative corporate sources. This technique significantly reduces hallucination rates and enables auditability—every output can be traced back to verifiable documents. Combined with output classifiers and HITL review, grounding transforms generative AI into a more trustworthy and explainable asset within the enterprise. The chapter also emphasizes measurable impact and continuous improvement as design principles for guardrails. Enterprises are encouraged to monitor metrics such as guardrail trigger counts, hallucination frequency, and fairness indices. Tools like MLflow, Evidently AI, and OpenLineage facilitate comprehensive auditing and traceability across model training and inference. These mechanisms support iterative guardrail refinement, aligning with the National Institute of Standards and Technology (NIST) AI Risk Management Framework’s “Measure” and “Manage” functions. Finally, the chapter outlines governance best practices and organizational structures to support responsible AI. From the Chief AI Ethics Officer to compliance managers and ML engineers, each role has a defined stake in ensuring that generative AI operates within safe, legal, and ethical boundaries. Global regulations, including the EU AI Act, U.S. agency guidelines, and China’s Interim Measures, are discussed to provide readers with an international compliance perspective. In conclusion, this chapter offers enterprise leaders, AI practitioners, and policy advocates a blueprint for operationalizing responsible AI through layered guardrails. It equips organizations with the tools, strategies, and governance models necessary to mitigate risks, maximize business value, and build stakeholder trust in the age of generative AI. As organizations scale AI across functions, these guardrails serve not as constraints but as enablers—empowering safe, innovative, and resilient AI adoption across industries. © The Editor(s) (if applicable) and The Author(s), under exclusive license to Springer Nature Switzerland AG 2026.
A26: S025 | B26: Abbas A.; Kovatchev V.; Lee M.; Shanavas N.; Ali M. | C26: 2025 | D26: Harnessing Open-Source LLMs for Tender Named Entity Recognition | E26: International Conference Recent Advances in Natural Language Processing, RANLP | F26: Conference paper | G26: 10.26615/978-954-452-098-4-001 | H26: Excluido | I26: E2 | J26: NER de entidades de licitaciones; la privacidad motiva usar LLM locales, pero no se detecta información sensible. | K26: Excluido | L26: Contratación pública | M26: General / documentos | N26: Inglés | O26: Inglés | T26: X | W26: =IF(AND(P26="X",OR(R26="X",S26="X",T26="X")),"Sí","No") -> No | AL26: No | AM26: No | AN26: No | AO26: Licitaciones de Singapur y Siemens | AP26: F1 > 85 % | AQ26: Abstract | AR26: In the public procurement domain, extracting accurate tender entities from unstructured text remains a critical, less explored challenge, because tender data is highly sensitive and confidential, and not available openly. Previously, state-of-the-art NLP models were developed for this task; however developing an NER model from scratch required huge amounts of data and resources. Similarly, performing fine-tuning of a transformer-based model like BERT requires training data, as a result posing challenges in training data cost, model generalization, and data privacy. To address these challenges, an emerging LLM such as GPT-4 in a Few-shot learning environment achieves SOTA performance comparable to fine-tuned models. However, being dependent on the closed-source commercial LLMs involves high cost and privacy concerns. In this study, we have investigated open-source LLMs like Mistral and LLAMA-3, focusing on the tender domain for the NER tasks on local consumer-grade CPUs in three different environments: Zero-shot, One-shot, and Few-shot learning. The motivation is to efficiently lessen costs compared to a cloud solution while preserving accuracy and data privacy. Similarly, we have utilized two datasets open-source from Singapore and closed-source commercially sensitive data provided by Siemens. As a result, all the open-source LLMs achieve above 85% F1-score on an open-source dataset and above 90% F1-score on a closed-source dataset. © 2025 Incoma Ltd. All rights reserved.
A27: S026 | B27: Gorskis H.; Strebko J.; Korņijenko J.; Zabiņako V.; Romanovs A. | C27: 2026 | D27: A Hybrid Approach to the Automatic Detection of Personal Data in Latvian-Language Texts | E27: Future Internet | F27: Article | G27: 10.3390/fi18070354 | H27: Núcleo | I27: N | J27: NER multilingüe con reglas para identificadores estructurados en comunicaciones empresariales; referente más cercano al escenario de este trabajo. | K27: Núcleo | L27: Empresarial (Teams, correo, documentos) | M27: Empresarial | N27: Letón | O27: Otra lengua | P27: X | S27: X | W27: =IF(AND(P27="X",OR(R27="X",S27="X",T27="X")),"Sí","No") -> Sí | AL27: No | AM27: No | AN27: No | AO27: Mensajes, correos y documentos en letón | AP27: No reporta valores en el abstract | AQ27: Abstract y texto completo | AR27: In the modern world, hybrid and fully remote work formats are becoming increasingly widespread. The volume of digital communication continues to grow, and the need to exchange documents and information through email, corporate messengers (such as Microsoft Teams), and collaborative workspaces is rising. Personal data is often involved in these exchanges, which increases the risk of unintentional disclosure. To comply with GDPR requirements and ensure information security, it is necessary to implement methods for the automatic detection of personal data. This task is particularly relevant for low-resource languages, such as Latvian, for which existing tools often operate with limited accuracy and efficiency. This work proposes a hybrid approach to the automatic detection of personal data in Latvian texts from Microsoft Teams messages, emails, and documents, combining a transformer-based NER model with rule-based detection of structured identifiers. The approach builds on a multilingual NER model, supplements it with Latvian-specific rules and structured-identifier detectors, and demonstrates the potential of adapted solutions to improve the accuracy and robustness of personal-data detection in real-world workflows. © 2026 by the authors.
A28: S027 | B28: Rai A.; Ali M.L.; Ur Rahim M.A.; Zaid M.; Jena P.; Bagaria R. | C28: 2026 | D28: Hybrid Contextual PII Redaction: An LLM-Regex System for Diverse Digital Assets | E28: Proceedings of the 4th IEEE International Conference on Interdisciplinary Approaches in Technology and Management for Social Innovation, IATMSI 2026 | F28: Conference paper | G28: 10.1109/IATMSI68868.2026.11466036 | H28: Núcleo | I28: N | J28: Combina LLM, regex para identificadores estructurados y NER de spaCy; supera a los enfoques de un solo método. | K28: Núcleo | L28: Documentos y archivos | M28: General / documentos | N28: No indicado | O28: No indicado o no aplica | P28: X | R28: X | T28: X | W28: =IF(AND(P28="X",OR(R28="X",S28="X",T28="X")),"Sí","No") -> Sí | AB28: X | AL28: No | AM28: No | AN28: No | AO28: PDF, Word, CSV, JSON, imágenes | AP28: Exactitud frente a enfoques de un solo método | AQ28: Abstract | AR28: The proliferation of digital data necessitates robust and automated solutions for Personally Identifiable Information (PII) protection, driven by regulatory mandates such as the General Data Protection Regulation (GDPR) and the California Consumer Privacy Act (CCPA). Traditional, manual, or purely rule-based redaction methods are inherently prone to error and fail to scale effectively for large, diverse datasets. This paper presents the Hybrid PII Detection Engine (HPDE), an intelligent, automated tool designed to accurately redact PII from a wide range of file formats, including images, portable document formats (PDFs), Microsoft Word documents (.docx), comma-separated values (CSV), and JavaScript object notation (JSON) files. The HPDE integrates a multi-layered detection strategy: it leverages the advanced contextual understanding of the Google Gemini Pro Large Language Model (LLM) for high-accuracy identification of ambiguous entities, supplementing this with deterministic Regular Expressions (Regex) for structured PII (e.g., Aadhaar, PAN) and efficient 1 ocal N amed Entity R ecognition (NER) using the spaCy library (specifically the e n_core_web_sm model). The system's backend is implemented using the robust Python Django framework. Furthermore, the paper details file-specific redaction techniques, incorporating Optical Character Recognition (OCR) via PyTesseract for handling text in image-based files and crucial security features such as metadata wiping (utilizing PIL, PyMuPDF, and python-docx) and verifiable watermarking (implemented via OpenCV and PyMuPDF). Benchmarking results confirm that the HPDE a chieves s uperior a ccuracy and versatility compared to conventional single-method approaches. © 2026 IEEE.
A29: S028 | B29: Naresh P.; Kushwaha S.; Prabudh S.; Eligar S.S.; Nethravathi V.; Radhika K. | C29: 2026 | D29: BharatPII Shield: An Intelligent System for Real-Time Detection and Protection of Indian Personally Identifiable Information | E29: 7th International Conference on Inventive Research in Computing Applications, ICIRCA 2026 - Proceedings | F29: Conference paper | G29: 10.1109/ICIRCA69024.2026.11570613 | H29: Núcleo | I29: N | J29: Extensión de navegador que detecta identificadores indios en el dispositivo antes de enviarlos; análogo a la protección previa al envío. | K29: Núcleo | L29: Gobierno / identidad | M29: Gobierno / identidad | N29: Multilingüe (India) | O29: Multilingüe | P29: X | V29: X | W29: =IF(AND(P29="X",OR(R29="X",S29="X",T29="X")),"Sí","No") -> No | Y29: X | Z29: X | AB29: X | AC29: X | AL29: Sí | AM29: No | AN29: No | AO29: 650 documentos sintéticos | AP29: Exactitud 93,3 %; falsos positivos < 4 %; < 1 s | AQ29: Abstract | AR29: The rapid shift of India toward digital-first governance and digital financial services has created an emergency situation which requires immediate action because people unintentionally disclose their sensitive Personally Identifiable Information (PII)including Aadhaar numbers and Permanent Account Numbers (PAN)and Driving License details and Voter IDs and phone numbers and email addresses and financial instrument numbers and online document submissions and web form interactions. Most digital workflows require users to upload their documents because this method depends on post-upload server-side validation which leads to data leakage during user action. The existing global PII protection tools create an additional problem because they provide almost no assistance to Indian government-issued identifier formats and structured alphanumeric patterns and multilingual scripts which appear on Indian identity documents. The research introduces BharatPII Shield which functions as a privacy-protecting browser extension that operates on users' devices to process text through Tesseract OCR while identifying sensitive identity data using its specialized regex processing system. The system architecture consists of five interconnected modules which include an OCR Processing Module that uses intelligent image preprocessing and a PII Detection Engine which identifies both Indian and standard identifiers and a Risk Assessment Engine that evaluates document sensitivity through three levels and a Selective Redaction Engine which enables full masking partial masking and token-based replacement and a Chrome Extension Integration layer which functions as a client-side firewall. The empirical evaluation used a dataset of 650 synthetic documents from multiple sources to assess the system. The project results demonstrate a detection accuracy of 93.3% across three document types which include Aadhaar and PAN and Driving License documents. The system achieves an OCR accuracy rate of about 92% for identity documents which contain printed text. The system produces false positive results at a rate which stays below 4%. The system maintains response times which never exceed one second thus fulfilling requirements for real-time use. The system functions completely on user devices while using AES-256 and Fernet encryption methods without needing to send any document information to the cloud. © 2026 IEEE.
A30: S029 | B30: Elbarbary O.; Rasslan M.; El Bolock A.; Sabty C. | C30: 2025 | D30: Hybrid AI for Arabic Sensitive Data Detection: Enhancing Privacy Compliance in Egypt | E30: International Journal of Safety and Security Engineering | F30: Article | G30: 10.18280/ijsse.150602 | H30: Núcleo | I30: N | J30: BERT más reglas para identificadores rígidos (ID nacional, IP, MAC, teléfono); el híbrido supera a cada estrategia sola. | K30: Núcleo | L30: Gobierno / general | M30: Gobierno / identidad | N30: Árabe | O30: Otra lengua | P30: X | R30: X | S30: X | W30: =IF(AND(P30="X",OR(R30="X",S30="X",T30="X")),"Sí","No") -> Sí | Z30: X | AB30: X | AH30: X | AL30: No | AM30: No | AN30: No | AO30: Texto árabe y datos estructurados | AP30: F1 92 % | AQ30: Abstract | AR30: We present a hybrid framework that combines BERT-based Named Entity Recognition with rule-based detectors for rigid identifiers (e.g., national IDs, IP/MAC addresses, phone numbers) and excludes these patterns from embedding-based classifiers on structured data. On unstructured Arabic text, our hybrid system achieves an F1 of 92%. In the structured setting, isolating formatted fields increases average F1 from 87% to 88%, with BiLSTM delivering the best performance. These results demonstrate that integrating deep contextual models with deterministic rules extends coverage of legally defined formats and outperforms single-strategy approaches. Future work will focus on developing a custom Arabic sensitive-entity corpus, validating on real datasets, and adding anonymization and encryption modules. ©2025 The authors.
A31: S030 | B31: Alshamrani H.A.; Alnahari M. | C31: 2026 | D31: Token-Level PII Detection with Symbolic, Sequential, and Transformer-Based Ensemble Models | E31: International Journal of Advanced Computer Science and Applications | F31: Article | G31: 10.14569/IJACSA.2026.0170653 | H31: Núcleo | I31: N | J31: Ensamble de reglas, diccionarios, CRF, BiLSTM y transformers; muestra la caída fuera de dominio. | K31: Núcleo | L31: General y financiero | M31: Financiero | N31: Inglés | O31: Inglés | P31: X | Q31: X | R31: X | S31: X | W31: =IF(AND(P31="X",OR(R31="X",S31="X",T31="X")),"Sí","No") -> Sí | AL31: No | AM31: No | AN31: No | AO31: ai4privacy pii-masking-43k, documentos financieros de Mendeley | AP31: F1 ponderado 0,975; 0,843 fuera de dominio | AQ31: Abstract | AR31: The rapid increase in unstructured digital information has led to an urgent demand for effective systems for safeguarding Personally Identifiable Information (PII) across multiple sectors and application domains. Existing single-model approaches frequently fail to resolve entity-type ambiguity in unstructured text, particularly when a token's PII status is context-dependent rather than syntactically predictable. This study presents EnsemblePII, a weighted voting ensemble that combines rule-based patterns, dictionary matching, Conditional Random Fields, Bi-LSTM sequence models, and transformerbased token classification. The ensemble applies a class-specific weighted voting strategy in which each model's per-entity influence is proportional to its per-class F1-score on a held-out validation set. The approach is assessed by using the ai4privacy/pii-masking-43k data set and the Mendeley Synthetic Financial Documents data set. EnsemblePII achieves a weighted F1 of 0.9749 on the general-purpose HF test set, marginally exceeding the strongest individual component (DistilBERT, F1 = 0.9744) on the in-distribution evaluation, and outperforming a published entity-span-level hybrid baseline by over 6 percentage points on the multi-class token-level task. On the Mendeley financial test set, Bi-LSTM and DistilBERT achieve F1 scores of 0.9959 and 0.9703, respectively, while the ensemble records 0.8433, revealing calibration sensitivity to entity classes absent from the weight calibration corpus. The results indicate that ensemblebased PII detection can improve in-distribution performance, but stable cross-domain generalization requires domain-aware calibration of ensemble weights; the DistilBERT component achieves the highest average F1 (0.9724) across both test sets, underscoring the value of transformer-based models for crossdomain PII detection. © (2026), (Science and Information Organization). All right reserved.
A32: S031 | B32: Sopkovič K.; Kupcová E.; Hládek D.; Pleva M. | C32: 2025 | D32: Efficient Acronymization of Sensitive Data Using Generative Models Fine-Tuned on LLM-Augmented Data | E32: Proceedings of the International Conference Radioelektronika, RADIOELEKTRONIKA | F32: Conference paper | G32: 10.1109/RADIOELEKTRONIKA65656.2025.11008388 | H32: Núcleo | I32: N | J32: Reemplaza datos sensibles por acrónimos con un T5 entrenado con datos generados por LLM, para conservar utilidad. | K32: Complementario | L32: General | M32: General / documentos | N32: No indicado | O32: No indicado o no aplica | S32: X | T32: X | W32: =IF(AND(P32="X",OR(R32="X",S32="X",T32="X")),"Sí","No") -> No | AL32: No | AM32: No | AN32: No | AO32: Datos aumentados con LLM | AP32: Supera a modelos NER | AQ32: Abstract | AR32: Data privacy is crucial today, especially with regulations such as GDPR. Data anonymization is key, but common methods often reduce data value. This paper explores the acronymization process, which replaces sensitive data with abbreviations, as a way to balance protection and data usability. We propose a new approach: using large language models (LLMs) to create training data for a T5 model, which we then fine-tune for acronymizing sensitive data. The results show that this method, especially when using LLMs like Gemma-9B-IT to augment the data, achieves promising results and outperforms existing Named Entity Recognition (NER) models in the specific task of acronymization. This offers a more efficient and scalable solution for anonymizing text data, contributing to both privacy protection and preserving the utility of data for analysis and research. © 2025 IEEE.
A33: S032 | B33: Beltrame M.; Conti M.; Guglielmin P.; Marchiori F.; Orazi G. | C33: 2024 | D33: RedactBuster: Entity Type Recognition from Redacted Documents | E33: Lecture Notes in Computer Science (including subseries Lecture Notes in Artificial Intelligence and Lecture Notes in Bioinformatics) | F33: Conference paper | G33: 10.1007/978-3-031-70890-9_23 | H33: Complementario | I33: C4 | J33: Ataque que infiere el tipo de entidad redactada a partir del contexto; usa TAB y propone una contramedida. | K33: Complementario | L33: Documentos redactados | M33: General / documentos | N33: Inglés | O33: Inglés | R33: X | S33: X | W33: =IF(AND(P33="X",OR(R33="X",S33="X",T33="X")),"Sí","No") -> No | AL33: No | AM33: No | AN33: No | AO33: Text Anonymization Benchmark (TAB) | AP33: Exactitud hasta 0,985 | AQ33: Abstract | AR33: The widespread exchange of digital documents in various domains has resulted in abundant private information being shared. This proliferation necessitates redaction techniques to protect sensitive content and user privacy. While numerous redaction methods exist, their effectiveness varies, with some proving more robust than others. As such, the literature proposes several deanonymization techniques, raising awareness of potential privacy threats. However, while none of these methods are successful against the most effective redaction techniques, these attacks only focus on the anonymized tokens and ignore the sentence context. In this paper, we propose RedactBuster, the first deanonymization model using sentence context to perform Named Entity Recognition on redacted text. Our methodology leverages fine-tuned state-of-the-art Transformers and Deep Learning models to determine the anonymized entity types in a document. We test RedactBuster against the most effective redaction technique and evaluate it using the publicly available Text Anonymization Benchmark (TAB). Our results show accuracy values up to 0.985 regardless of the document nature or entity type. In raising awareness of this privacy issue, we propose a countermeasure we call character evasion that helps strengthen the secrecy of sensitive information. Furthermore, we make our model and testbed open-source to aid researchers and practitioners in evaluating the resilience of novel redaction techniques and enhancing document privacy. © The Author(s), under exclusive license to Springer Nature Switzerland AG 2024.
A34: S033 | B34: Godbole S.; Bhabire R.; Gavali Y.; Shende P.; Pandit P.; Yenkikar A. | C34: 2026 | D34: AI Shredder: OCR and BERT-Driven Intelligent Document Redaction with Security Classification | E34: 2026 International Conference on Emerging Smart Computing and Informatics, ESCI 2026 | F34: Conference paper | G34: 10.1109/ESCI68015.2026.11493218 | H34: Complementario | I34: C3 | J34: OCR, regex y BERT con puntaje de riesgo por documento; la entrada es imagen, pero aporta la idea de clasificar por nivel de riesgo. | K34: Complementario | L34: Documentos escaneados | M34: Voz o imagen | N34: Inglés | O34: Inglés | P34: X | S34: X | V34: X | W34: =IF(AND(P34="X",OR(R34="X",S34="X",T34="X")),"Sí","No") -> Sí | AL34: No | AM34: No | AN34: No | AO34: 2.000 imágenes de RVL-CDIP con 4.847 entidades | AP34: Exactitud 79,65 %; F1 0,794; kappa 0,91 en nivel de riesgo | AQ34: Abstract | AR34: In enterprise, healthcare and legal sectors, secure document management is highly important. Manual redaction and masking by keywords are tedious and lack situational sensitivities. We introduce AI Shredder, the first combination of deep learning code that is built on top of an Optical Character Recognition (OCR), Regex patterns matching, Named Entities Recognition (NER), and transformed by BERT based networks into one unified pipeline. The new addition is a coherent combination of various detection modalities (OCR+ Regex structured entities; BERT contextual PII) with a risk-scoring system that allows making a clear classification by the level of risk: Low Confidentiality (risk score 0.35 or below), High Confidentiality (0.35 to 0.70), and Top Secret (0.70 and over). This justifiable method is in contrast to closed-box redaction systems. The system was tested on 2000 manually annotated RVLCDIP document images (125 per class, 4,847 entity-level annotations) with a accuracy of 79.65 and F1-score of 0.7940 and security-level agreement of 94.2% (Kappa: 0.91). Per-category analysis demonstrates good results with the structured documents (forms: 86.36, invoices: 86.79, budgets: 87.12) and indicates difficulties with the handwritten material (64.94%). The modular architecture is auditable with detailed redaction logs and can be used as a tool to meet the requirements of GDPR/HIPAA. © 2026 IEEE.
A35: S034 | B35: Kocaman V.; Mellah Y.; Ul Haq H.; Talby D. | C35: 2023 | D35: Automated De-Identification of Arabic Medical Records | E35: ArabicNLP 2023 - 1st Arabic Natural Language Processing Conference, Proceedings | F35: Conference paper | H35: Núcleo | I35: N | J35: BERT y BiLSTM-CNN con un analizador contextual para las entidades que el modelo omite. | K35: Núcleo | L35: Clínico | M35: Salud / clínico | N35: Árabe | O35: Otra lengua | P35: X | R35: X | S35: X | W35: =IF(AND(P35="X",OR(R35="X",S35="X",T35="X")),"Sí","No") -> Sí | AL35: No | AM35: No | AN35: No | AO35: i2b2 2014 traducido al árabe | AP35: F1 micro 0,94–0,98 en 17 entidades | AQ35: Abstract | AR35: As Electronic Health Records (EHR) become ubiquitous in healthcare systems worldwide, including in Arabic-speaking countries, the dual imperative of safeguarding patient privacy and leveraging data for research and quality improvement grows. This paper presents a first-of-its-kind automated de-identification pipeline for medical text specifically tailored for the Arabic language. This includes accurate medical Named Entity Recognition (NER) for identifying personal information; data obfuscation models to replace sensitive entities with fake entities; and an implementation that natively scales to large datasets on commodity clusters. This research makes two contributions. First, we adapt two existing NER architectures—BERT For Token Classification (BFTC) and BiLSTM-CNN-Char – to accommodate the unique syntactic and morphological characteristics of the Arabic language. Comparative analysis suggests that BFTC models outperform Bi-LSTM models, achieving higher F1 scores for both identifying and redacting personally identifiable information (PII) from Arabic medical texts. Second, we augment the deep learning models with a contextual parser engine to handle commonly missed entities. Experiments show that the combined pipeline demonstrates superior performance with micro F1 scores ranging from 0.94 to 0.98 on the test dataset, which is a translated version of the i2b2 2014 de-identification challenge, across 17 sensitive entities. This level of accuracy is in line with that achieved with manual de-identification by domain experts, suggesting that a fully automated and scalable process is now viable. © 2023 Association for Computational Linguistics.
A36: S035 | B36: Schultenkämper S.; Bäumer F.S. | C36: 2024 | D36: Privacy Risks in German Patient Forums: A NER-Based Approach to Enrich Digital Twins | E36: Communications in Computer and Information Science | F36: Conference paper | G36: 10.1007/978-3-031-48981-5_9 | H36: Complementario | I36: C4 | J36: Usa NER para extraer datos de salud y mostrar el riesgo de agregación; es un análisis de riesgo, no un mecanismo de protección. | K36: Núcleo | L36: Salud / foros | M36: Salud / clínico | N36: Alemán | O36: Otra lengua | R36: X | W36: =IF(AND(P36="X",OR(R36="X",S36="X",T36="X")),"Sí","No") -> No | AK36: X | AL36: No | AM36: No | AN36: No | AO36: Foros de pacientes en alemán | AP36: P 0,867; R 0,963; F1 0,912 | AQ36: Abstract | AR36: The online sharing of personal health data by individuals has raised privacy concerns. This paper presents a Named Entity Recognition (NER)-based analysis to detect potential privacy risks in German patient forums. The objective is to extract sensitive information from user-generated texts and augment existing digital profiles of users to demonstrate the potential threats posed by the aggregation of information. To achieve this, we trained a NER model on a large corpus of German patient forum texts and evaluated its performance using standard metrics. The results show that the NER model can effectively extract health-related information from German texts with a micro-average precision of 0.8666, a recall of 0.9633 and an F1-score of 0.9124. This enables the creation of Digital Twins that accurately reflect the health-related characteristics of individuals. However, when this information is combined with data from different platforms, it poses a potential threat to users’ privacy and underlines the need to warn users. © 2024, The Author(s), under exclusive license to Springer Nature Switzerland AG.
A37: S036 | B37: Ngo P.D.; Tejedor M.; Svenning T.O.; Chomutare T.; Budrionis A.; Dalianis H. | C37: 2024 | D37: Deidentifying a Norwegian clinical corpus - An effort to create a privacy-preserving Norwegian large clinical language model | E37: CALD-pseudo 2024 - Workshop on Computational Approaches to Language Data Pseudonymization, Proceedings of the Workshop | F37: Conference paper | H37: Núcleo | I37: N | J37: Desidentificación y seudonimización con NorDeid, ampliado con regex para tipos específicos. | K37: Núcleo | L37: Clínico | M37: Salud / clínico | N37: Noruego | O37: Otra lengua | P37: X | R37: X | W37: =IF(AND(P37="X",OR(R37="X",S37="X",T37="X")),"Sí","No") -> Sí | AL37: No | AM37: No | AN37: No | AO37: Nueve millones de notas clínicas | AP37: No reporta valores en el abstract | AQ37: Abstract | AR37: This study discusses the methods and challenges of deidentifying and pseudonymizing Norwegian clinical text for research purposes. The results of the NorDeid tool for deidentification and pseudonymization on different types of protected health information were evaluated and discussed, as well as the extension of its functionality with regular expressions to identify specific types of sensitive information. This research used a clinical corpus of adult patients treated in a gastro-surgical department in Norway, which contains approximately nine million clinical notes. The study also highlights the challenges posed by the unique language and clinical terminology of Norway and emphasizes the importance of protecting privacy and the need for customized approaches to meet legal and research requirements. ©2024 Association for Computational Linguistics.
A38: S037 | B38: Mancera G.; Morales A.; Fierrez J.; Tolosana R.; Peña A.; Lopez-Duran M.; Jurado F.; Ortigosa A. | C38: 2026 | D38: PBa-LLM: Privacy- and Bias-Aware NLP Using Named-Entity Recognition (NER) | E38: Lecture Notes in Computer Science | F38: Conference paper | G38: 10.1007/978-3-032-09368-4_1 | H38: Núcleo | I38: N | J38: Compara anonimizadores basados en Presidio, FLAIR, BERT y GPT y mide su efecto sobre la tarea; útil como antecedente de Presidio. | K38: Núcleo | L38: Recursos humanos / hojas de vida | M38: Empresarial | N38: Inglés | O38: Inglés | R38: X | S38: X | T38: X | U38: X | W38: =IF(AND(P38="X",OR(R38="X",S38="X",T38="X")),"Sí","No") -> No | X38: X | AE38: X | AL38: No | AM38: Sí | AN38: No | AO38: 24.000 perfiles de candidatos | AP38: Desempeño de la tarea de puntuación | AQ38: Abstract | AR38: The use of Natural Language Processing (NLP) in high-stakes AI-based applications has increased significantly in recent years, especially since the emergence of Large Language Models (LLMs). However, despite their strong performance, LLMs introduce important legal/ethical concerns, particularly regarding privacy, data protection, and transparency. Due to these concerns, this work explores the use of Named-Entity Recognition (NER) to facilitate the privacy-preserving training (or adaptation) of LLMs. We propose a framework that uses NER technologies to anonymize sensitive information in text data, such as personal identities or geographic locations. An evaluation of the proposed privacy-preserving learning framework was conducted to measure its impact on user privacy and system performance in a particular high-stakes and sensitive setup: AI-based resume scoring for recruitment processes. The study involved two language models (BERT and RoBERTa) and six anonymization algorithms (based on Presidio, FLAIR, BERT, and different versions of GPT) applied to a database of 24,000 candidate profiles. The findings indicate that the proposed privacy preservation techniques effectively maintain system performance while playing a critical role in safeguarding candidate confidentiality, thus promoting trust in the experimented scenario. On top of the proposed privacy-preserving approach, we also experiment applying an existing approach that reduces the gender bias in LLMs, thus finally obtaining our proposed Privacy- and Bias-aware LLMs (PBa-LLMs). Note that the proposed PBa-LLMs have been evaluated in a particular setup (resume scoring), but are generally applicable to any other LLM-based AI application. © The Author(s), under exclusive license to Springer Nature Switzerland AG 2026.
A39: S038 | B39: Nandhini Priya P.; Philip T.; Yazhini K.; Chandrika R.R. | C39: 2026 | D39: Design and Implementation of an Automated PII Detection System using DeBERTaV2 and NLP | E39: Proceedings of the 2026 6th International Conference on Image Processing and Capsule Networks, ICIPCN 2026 | F39: Conference paper | G39: 10.1109/ICIPCN67432.2026.11438673 | H39: Núcleo | I39: N | J39: Compara cinco transformers para PII; DeBERTaV2 obtiene el mejor resultado. | K39: Núcleo | L39: Educación / investigación | M39: General / documentos | N39: No indicado | O39: No indicado o no aplica | S39: X | W39: =IF(AND(P39="X",OR(R39="X",S39="X",T39="X")),"Sí","No") -> No | X39: X | Y39: X | Z39: X | AA39: X | AL39: No | AM39: No | AN39: No | AO39: No indicado | AP39: Exactitud cercana a 96 %; P, R y F1 | AQ39: Abstract | AR39: This project focuses on the development and implementation of an intelligent system that automatically detects and removes Personally Identifiable Information (PII) from textual data using advanced Natural Language Processing (NLP) and deep learning techniques. The proposed model employs the DeBERTaV2 transformer, an enhanced version of BERT, fine-tuned for token classification and Named Entity Recognition (NER) tasks. The system identifies sensitive information such as names, emails, addresses, and phone numbers while ensuring data privacy and maintaining semantic consistency. Python and Streamlit are used for system development, providing an interactive interface for text analysis and redaction. To validate performance, multiple deep learning models - BERT, RoBERTa, DistilBERT, ALBERT, and DeBERTaV2 - were compared using precision, recall, F1-score, and accuracy metrics. The results demonstrate that DeBERTaV2 outperforms other transformer-based models, achieving an overall accuracy of 96context-aware PII detection significantly improves data protection and reduces the need for manual intervention, supporting secure data handling in educational and research domains. © 2026 IEEE.
A40: S039 | B40: Abhijith B.; Vanama B.; Reddy P.V.; Harini K.; Bhavana C. | C40: 2026 | D40: RE-DACT: An Intelligent Multi-Modal Automated Redaction System | E40: Proceedings of the 3rd International Conference on Innovations in Cybersecurity and Data Science, ICICDS 2026 | F40: Conference paper | G40: 10.1109/ICICDS70526.2026.11604798 | H40: Núcleo | I40: N | J40: Dos capas: regex para 11 identificadores estructurados y spaCy para entidades contextuales; respalda asignar el detector por tipo. | K40: Complementario | L40: Documentos (India) | M40: Gobierno / identidad | N40: Inglés | O40: Inglés | P40: X | R40: X | W40: =IF(AND(P40="X",OR(R40="X",S40="X",T40="X")),"Sí","No") -> Sí | X40: X | AA40: X | AB40: X | AC40: X | AD40: X | AF40: X | AL40: No | AM40: No | AN40: No | AO40: PDF en inglés | AP40: F1 98,4–100 % (regex); 74,2–83,7 % (NER) | AQ40: Abstract | AR40: India generates enormous volumes of documents daily across healthcare, legal, banking, human resources, and government sectors. Each document frequently contains sensitive Personally Identifiable Information (PII) including Aadhaar numbers, PAN cards, Voter IDs, IFSC codes, UPI handles, and bank account details. Before these documents are shared for audits, court submissions, or inter-departmental exchange they must be redacted to protect individual privacy and comply with the Digital Personal Data Protection (DPDP) Act 2023, the Aadhaar Act 2016, and RBI Master Directions. RE-DACT is a fullstack, AI-powered document redaction platform that automatically detects and permanently removes PII from PDF documents with specific focus on Indian identifier formats. The platform implements a two-layer detection engine: a pure-regex Layer 1 for eleven structured Indian identifiers achieving F1 scores of 98.4-100 %, and a spaCy en_core_web_lg transformerbased NER Layer 2 for unstructured entities (PERSON, ADDRESS, ORG, DATE) achieving 7 4. 2 - 8 3. 7 % F1. Detected entities are permanently removed at the byte level using PyMuPDF's apply_redactions() making recovery forensically impossible. The system is built on a microservices architecture comprising a React frontend, Node.js/Express backend, Python/FastAPI NLP sidecar, Node.js worker service, MongoDB with GridFS, RabbitMQ job queue, and Redis status cache all orchestrated via Docker Compose. A four-stage document lifecycle (Queued → Processing → Review → Done) enforces mandatory human-in-the-loop approval required for legal compliance. Seven domain presets (General, Legal, Medical, Finance, HR, Government, Research) enable context-appropriate entity activation. The current implementation targets English-language PDF documents; extension to Indic scripts is identified as the primary direction for future work. © 2026 IEEE.
A41: S040 | B41: Azmi F.; Tong R. | C41: 2025 | D41: LLM-Enhanced Spoken Named Entity Recognition Leveraging ASR N-Best Hypotheses | E41: Proceedings of 2025 International Conference on Asian Language Processing, IALP 2025 | F41: Conference paper | G41: 10.1109/IALP68296.2024.11156876 | H41: Complementario | I41: C3 | J41: Corrige errores del ASR con un LLM antes de etiquetar PII; la entrada es audio. | K41: Excluido | L41: Voz / transcripción | M41: Voz o imagen | N41: Inglés | O41: Inglés | T41: X | W41: =IF(AND(P41="X",OR(R41="X",S41="X",T41="X")),"Sí","No") -> No | AL41: No | AM41: No | AN41: No | AO41: Habla en inglés | AP41: F1 de etiquetado de PII | AQ41: Abstract | AR41: Identifying Personally Identifiable Information (PII) from spoken documents is crucial for privacy preservation in speech processing. Unlike written text, spoken language exhibits greater variability due to factors such as accent, emotion, hesitation, and vocabulary choice, which can complicate PII detection. A standard approach involves using Automatic Speech Recognition (ASR) followed by Named Entity Recognition (NER) to identify PII from speech input. However, the accuracy of ASR is pivotal for effective PII discovery, and the inherent complexities of speech production can lead to ASR errors, hindering PII detection. To address this limitation, we propose a novel method that integrates an LLM-based module after ASR to perform error correction and PII tagging, leveraging the richer contextual information available in the n-best outputs from the ASR system. We systematically investigate various prompting strategies, including Zero-shot, Few-shot, and Chain-of-Thought prompting, to guide the LLM. Our experimental results demonstrate that the LLM-based error correction yields a substantial F1 improvement on PII tagging. Furthermore, incorporating the n-best list consistently improves the F1 score, and Chain-of-Thought prompting outperforms other strategies like Zero-shot and Few-shot prompting. © 2025 IEEE.
A42: S041 | B42: Vakili T.; Henriksson A.; Dalianis H. | C42: 2025 | D42: Data-Constrained Synthesis of Training Data for De-Identification | E42: Proceedings of the Annual Meeting of the Association for Computational Linguistics | F42: Conference paper | G42: 10.18653/v1/2025.acl-long.1329 | H42: Complementario | I42: C1 | J42: Genera corpus clínicos sintéticos con LLM para entrenar NER de desidentificación; incluye datos en español. | K42: Núcleo | L42: Clínico | M42: Salud / clínico | N42: Sueco y español | O42: Español (solo o con otras lenguas) | S42: X | T42: X | W42: =IF(AND(P42="X",OR(R42="X",S42="X",T42="X")),"Sí","No") -> No | AL42: No | AM42: No | AN42: No | AO42: Textos clínicos en sueco y español | AP42: Caída pequeña de F1 con datos sintéticos | AQ42: Abstract | AR42: Many sensitive domains - such as the clinical domain - lack widely available datasets due to privacy risks. The increasing generative capabilities of large language models (LLMs) have made synthetic datasets a viable path forward. In this study, we domain-adapt LLMs to the clinical domain and generate synthetic clinical texts that are machine-annotated with tags for personally identifiable information using capable encoder-based NER models. The synthetic corpora are then used to train synthetic NER models. The results show that training NER models using synthetic corpora incurs only a small drop in predictive performance. The limits of this process are investigated in a systematic ablation study - using both Swedish and Spanish data. Our analysis shows that smaller datasets can be sufficient for domain-adapting LLMs for data synthesis. Instead, the effectiveness of this process is almost entirely contingent on the performance of the machine-annotating NER models trained using the original data. © 2025 Association for Computational Linguistics.
A43: S042 | B43: Yu J.; Zhou J.; Ding Y.; Zhang L.; Guo Y.; Sato H. | C43: 2024 | D43: Textual Differential Privacy for Context-Aware Reasoning with Large Language Model | E43: Proceedings - 2024 IEEE 48th Annual Computers, Software, and Applications Conference, COMPSAC 2024 | F43: Conference paper | G43: 10.1109/COMPSAC61105.2024.00135 | H43: Complementario | I43: C1 | J43: Privacidad diferencial textual para anonimizar el contexto antes de enviarlo al proveedor del LLM sin perder razonamiento. | K43: Complementario | L43: LLM / RAG | M43: LLM / asistentes | N43: No indicado | O43: No indicado o no aplica | V43: X | W43: =IF(AND(P43="X",OR(R43="X",S43="X",T43="X")),"Sí","No") -> No | AL43: Sí | AM43: Sí | AN43: Sí | AO43: No indicado | AP43: Pérdida de privacidad y capacidad de razonamiento | AQ43: Abstract | AR43: Large language models (LLMs) have demonstrated proficiency in various language tasks but encounter difficulties in specific domain or scenario. These challenges are mitigated through prompt engineering techniques such as retrieval-augmented generation, which improves performance by integrating contextual information. However, concerns regarding the privacy implications of context-aware reasoning architectures persist, particularly regarding the transmission of sensitive data to LLMs service providers, potentially compromising personal privacy. To mitigate these challenges, this paper introduces Tex-tual Differential Privacy, a novel paradigm aimed at safeguarding user privacy in LLMs-based context-aware reasoning. The proposed Differential Embedding Hash algorithm anonymizes sensitive information while maintaining the reasoning capability of LLMs. Additionally, a quantification scheme for privacy loss is proposed to better understand the trade-off between privacy protection and loss. Through rigorous analysis and experimentation, the effectiveness and robustness of the proposed paradigm in mitigating privacy risks associated with context-aware reasoning tasks are demonstrated. This paradigm addresses privacy concerns in context-aware reasoning architectures, enhancing the trust and utility of LLMs in various applications. © 2024 IEEE.
A44: S043 | B44: Zhang L.; Li Y.-F.; Zhang Y. | C44: 2024 | D44: SIDF: A Desensitization Framework for Sensitive Information in Chinese Medical Report Images | E44: Proceedings of the 2024 27th International Conference on Computer Supported Cooperative Work in Design, CSCWD 2024 | F44: Conference paper | G44: 10.1109/CSCWD61410.2024.10580575 | H44: Complementario | I44: C3 | J44: Desensibiliza informes médicos en imagen con OCR y NER; la entrada es imagen. | K44: Excluido | L44: Imágenes médicas | M44: Voz o imagen | N44: Chino | O44: Otra lengua | R44: X | V44: X | W44: =IF(AND(P44="X",OR(R44="X",S44="X",T44="X")),"Sí","No") -> No | AL44: No | AM44: No | AN44: No | AO44: Imágenes de informes médicos | AP44: Índice propio de desensibilización válida | AQ44: Abstract | AR44: Medical report images have become the main information resource in intelligent medical treatment, online consultation, and medical research. While facilitating the use of relevant personnel, information security and privacy protection are particularly important. At present, there are related technologies for image desensitization or medical text desensitization, but there is a lack of research on Chinese medical report image desensitization. Thus, this paper proposes a desensitization framework for sensitive information (SIDF) in Chinese medical report images. SIDF contains five modules: sensitive information construction, text detection and text recognition, sensitive information extraction, sensitive information location, and sensitive information desensitization. Because all modules in SIDF can be flexibly designed according to specific requirements, it is convenient to use SIDF. In addition, we design an index of valid desensitization (VD) for measuring the desensitization performance of algorithms. We evaluate SIDF on the Chinese medical report images collected from Internet and private contributions. Experimental results show that our proposed desensitization framework is effective. © 2024 IEEE.
A45: S044 | B45: Dhingra P.; Agrawal S.; Veerappan C.S.; Ho T.N.; Chng E.S.; Tong R. | C45: 2024 | D45: Speech de-identification data augmentation leveraging large language model | E45: Proceedings of 2024 International Conference on Asian Language Processing, IALP 2024 | F45: Conference paper | G45: 10.1109/IALP63756.2024.10661176 | H45: Complementario | I45: C3 | J45: Aumenta datos con un LLM para desidentificar habla; la entrada es audio. | K45: Excluido | L45: Voz / transcripción | M45: Voz o imagen | N45: Inglés | O45: Inglés | R45: X | T45: X | W45: =IF(AND(P45="X",OR(R45="X",S45="X",T45="X")),"Sí","No") -> No | AL45: No | AM45: No | AN45: No | AO45: Texto sintético con estilo oral | AP45: F1 NER | AQ45: Abstract | AR45: This work addresses the challenge of limited real-world speech data in speech de-identification, the process of removing Personally Identifiable Information (PII). We formulate speech de-identification as a named entity recognition (NER) task specifically for spoken English. To overcome data scarcity and enhance NER performance, we propose a data augmentation approach. This approach leverages a large language model to generate synthetic speech style text data enriched with diverse PII entities. The generated data undergoes an iterative process using a customized NER model for semi-automatic PII annotation. Our analysis demonstrates the effectiveness of this data augmentation strategy in significantly improving NER performance on spoken language text. Furthermore, to gain deeper insights into the specific errors made during NER, we employ performance analysis using alternative evaluation metrics. © 2024 IEEE.
A46: S045 | B46: Sujith V.M.; Gopu A.P.; Abinaya S.; Gokul B.; Bhavadharani S.; Baby K. | C46: 2026 | D46: Personal Data Privacy Auditor - A Hybrid Framework for Local PII Detection and Browser Tracker Analysis | E46: Conference Proceedings - 1st International Conference on Advancing Sustainable Solutions through Technologies, ICASST 2026 | F46: Conference paper | G46: 10.1109/ICASST68917.2026.11484150 | H46: Núcleo | I46: N | J46: Regex, heurísticas y validación de Luhn para correos, teléfonos, documentos, tarjetas y claves secretas; respalda los validadores. | K46: Núcleo | L46: Archivos personales y empresariales | M46: Empresarial | N46: No indicado | O46: No indicado o no aplica | P46: X | V46: X | W46: =IF(AND(P46="X",OR(R46="X",S46="X",T46="X")),"Sí","No") -> No | Y46: X | Z46: X | AB46: X | AC46: X | AG46: X | AL46: No | AM46: No | AN46: No | AO46: Archivos de texto, PDF, DOCX e imágenes | AP46: Precisión y recall | AQ46: Abstract | AR46: Nowadays, personal data is being created, stored, and shared across numerous platforms and hardware. With ongoing privacy inflections and data breaches, both individuals and organizations need a trustworthy solution to assist them in the discovery and protection of sensitive information they have access to. The Personal Data Privacy Auditor is a helpful Python-based solution that automates the discovery, classification, and reporting of Personally Identifiable Information (PII) across a variety of file types (text, PDF, DOCX, images, and compressed file formats). The system uses regular expressions, heuristics, Luhn algorithm checks, and Optical Character Recognition (OCR) technology to identify a variety of PII elements including but not limited to email addresses, phone numbers, Aadhaar / PAN numbers, credit card numbers, and secret keys. All discovered PII is masked or hashed and stored in order to protect the confidentiality of information during the auditing process. The appropriately named "Self-Assessment Tool"(SAT) generates statistical reporting and precision-recall examination for evaluating detection accuracy. Moreover, in contrast to any deployed solution using networked security distribution, the auditor functions completely offline, which preserves user privacy when they self-audit their data hygiene remotely. The auditor offers additional education regarding possible privacy threat vectors and helps firms with the legal framework of data protection, and provides a rationale for feature development (e.g. browser tracking identification or dashboard visualization). © 2026 IEEE.
A47: S046 | B47: Sheela S.; Akshatha P.S.; Kushalatha M.R.; Kumar S.M.D. | C47: 2026 | D47: Toward a Secure Future: An Integrated Framework for PII Detection Using NLP and Visual Analysis | E47: IEEE Access | F47: Article | G47: 10.1109/ACCESS.2026.3669713 | H47: Núcleo | I47: N | J47: Compara regex, spaCy, BERT e híbrido sobre texto OCR; el híbrido supera a cada componente solo. | K47: Complementario | L47: Documentos de identidad | M47: Gobierno / identidad | N47: Inglés (India) | O47: Inglés | P47: X | R47: X | S47: X | V47: X | W47: =IF(AND(P47="X",OR(R47="X",S47="X",T47="X")),"Sí","No") -> Sí | AL47: No | AM47: No | AN47: No | AO47: Conjunto sintético de PII india | AP47: F1 regex 0,445; spaCy 0,166; BERT 0,042; híbrido 0,515 | AQ47: Abstract | AR47: Safeguarding Personally Identifiable Information (PII) is critical to prevent data breaches and identity theft in the era of digital services. This paper presents a hybrid PII detection and secure verification system that integrates rule-based regular expressions, transformer-based spaCy NLP, BERT models, and a Swin Transformer-based FasterRCNN pipeline. While text-based methods (Regex, SpaCy, BERT) excel at structured and contextual PII detection from OCR-processed text, the Swin Transformer provides vision-based detection capability for document images, handling complex layouts and visual cues often missed by traditional pipelines. It is observed that the empirical evaluation on a synthetic Indian PII dataset shows a significant performance improvement: the Regex method achieves an F1-score of 0.445, spacy reaches 0.166, and BERT alone achieves 0.042. The hybrid model, which combines these, yields an improved F1-score of 0.515, while the Swin Transformer model outperforms all others with an F1-score of 0.978, demonstrating near-perfect performance for image-based PII detection. A blockchain-backed double hashing mechanism, SHA-256, provides tamper-proof storage of PII fingerprints, while OTPbased authentication secures system access. In this work, it is proposed to use both OCR and vision-based detection in the scanned PDFs and images for robust and secure PII verification. This framework provides an interpretable, scalable, and privacy-preserving identity verification solution that improves upon the accuracy and layout awareness compared to the previous methods. © 2013 IEEE.
A48: S047 | B48: Dunstan J.; Vakili T.; Miranda L.; Villena F.; Aracena C.; Quiroga T.; Vera P.; Viteri Valenzuela S.; Rocco V. | C48: 2024 | D48: A pseudonymized corpus of occupational health narratives for clinical entity recognition in Spanish | E48: BMC Medical Informatics and Decision Making | F48: Article | G48: 10.1186/s12911-024-02609-w | H48: Núcleo | I48: N | J48: Corpus en español anotado con PII; compara el efecto de enmascarar y seudonimizar sobre una tarea posterior. | K48: Complementario | L48: Clínico (salud ocupacional) | M48: Salud / clínico | N48: Español | O48: Español (solo o con otras lenguas) | S48: X | W48: =IF(AND(P48="X",OR(R48="X",S48="X",T48="X")),"Sí","No") -> No | AL48: No | AM48: Sí | AN48: No | AO48: 1.787 anamnesis anotadas | AP48: Desempeño del NER clínico en texto original, enmascarado y seudonimizado | AQ48: Abstract | AR48: Despite the high creation cost, annotated corpora are indispensable for robust natural language processing systems. In the clinical field, in addition to annotating medical entities, corpus creators must also remove personally identifiable information (PII). This has become increasingly important in the era of large language models where unwanted memorization can occur. This paper presents a corpus annotated to anonymize personally identifiable information in 1,787 anamneses of work-related accidents and diseases in Spanish. Additionally, we applied a previously released model for Named Entity Recognition (NER) trained on referrals from primary care physicians to identify diseases, body parts, and medications in this work-related text. We analyzed the differences between the models and the gold standard curated by a physician in detail. Moreover, we compared the performance of the NER model on the original narratives, in narratives where personal information has been masked, and in texts where the personal data is replaced by another similar surrogate value (pseudonymization). Within this publication, we share the annotation guidelines and the annotated corpus. © The Author(s) 2024.
A49: S048 | B49: Nayak S.P.; Pasumarthi S.; Rajagopal B.; Verma A.K. | C49: 2024 | D49: GDPR Compliant ChatGPT Playground | E49: International Conference on Emerging Technologies in Computer Science for Interdisciplinary Applications, ICETCS 2024 | F49: Conference paper | G49: 10.1109/ICETCS61022.2024.10543557 | H49: Núcleo | I49: N | J49: Valida el prompt con un NER corporativo antes de enviarlo a ChatGPT y avisa al usuario; es el antecedente más cercano al proxy de este trabajo. | K49: Complementario | L49: Empresarial / LLM | M49: LLM / asistentes | N49: No indicado | O49: No indicado o no aplica | Q49: X | R49: X | W49: =IF(AND(P49="X",OR(R49="X",S49="X",T49="X")),"Sí","No") -> No | AL49: Sí | AM49: No | AN49: No | AO49: Documentos corporativos etiquetados | AP49: No reporta métricas en el abstract | AQ49: Abstract (texto completo no disponible) | AR49: ChatGPT is an AI based conversational tool developed by OpenAPI on the design principles of Large Language Model (LLM) and a publicly accessible tool. ChatGPT has increasingly becoming popular tool for enabling applications involving interactive and contextual search across corporate companies, profit/non-profit organizations, educational/medical institutions, and researcher's community to name a few.The corporate companies are abided by GDPR (General Data Protection Regulation) compliance checks and restricted to share confidential, personal or sensitive information's (hereinafter referred as critical data) into public domains. As ChatGPT server is hosted outside corporate boundaries, to fulfil GDPR compliance check, the corporate companies must have necessary systems in place of any data leaving outside of corporate boundaries.We are proposing a novel solution in identifying GDPR noncompliant DPP (Data Privacy and Protection) entities from the prompt query given to ChatGPT. To achieve this, from the corporate documents we first manually tag critical entities from 'named entity tagging tool' in building the corporate specific DPP entities knowledgebase, build custom NER (Named Entity Recognition) model on top of prebuilt corporate specific DPP entities knowledgebase, an ChatGPT playground interface to accept any user's prompt query, before firing the query to ChatGPT we validate the user's prompt query against custom NER model to detect if any corporate specific DPP entities are present, warn the user by highlighting the corporate specific DPP entities if present to facilitate user in negating the same, we enabled feedback loop from the user for the highlighted corporate specific DPP entities to improvise the custom NER model and logging all the input prompt queries fired to ChatGPT to enable corporate auditing process by using techniques from Natural Language Processing (NLP), Information Extraction, Information Retrieval (IR) and Custom NER model. © 2024 IEEE.
A50: S049 | B50: Liu L.; Perez-Concha O.; Nguyen A.; Bennett V.; Jorm L. | C50: 2022 | D50: De-identifying Australian hospital discharge summaries: An end-to-end framework using ensemble of deep learning models | E50: Journal of Biomedical Informatics | F50: Article | G50: 10.1016/j.jbi.2022.104215 | H50: Núcleo | I50: N | J50: Ensambles de modelos NER para desidentificar resúmenes de alta; reporta F1 con coincidencia estricta. | K50: Núcleo | L50: Clínico | M50: Salud / clínico | N50: Inglés | O50: Inglés | R50: X | S50: X | W50: =IF(AND(P50="X",OR(R50="X",S50="X",T50="X")),"Sí","No") -> No | X50: X | Z50: X | AA50: X | AB50: X | AD50: X | AL50: No | AM50: No | AN50: No | AO50: 600 resúmenes de alta e i2b2 2014 | AP50: F1 99,16 %; 96,24 % estricto en i2b2 | AQ50: Abstract | AR50: Electronic Medical Records (EMRs) contain clinical narrative text that is of great potential value to medical researchers. However, this information is mixed with Personally Identifiable Information (PII) that presents risks to patient and clinician confidentiality. This paper presents an end-to-end de-identification framework to automatically remove PII from Australian hospital discharge summaries. Our corpus included 600 hospital discharge summaries which were extracted from the EMRs of two principal referral hospitals in Sydney, Australia. Our end-to-end de-identification framework consists of three components: (1) Annotation: labelling of PII in the 600 hospital discharge summaries using five pre-defined categories: person, address, date of birth, individual identification number, phone/fax number; (2) Modelling: training six named entity recognition (NER) deep learning base-models on balanced and imbalanced datasets; and evaluating ensembles that combine all six base-models, the three base-models with the best F1 scores and the three base-models with the best recall scores respectively, using token-level majority voting and stacking methods; and (3) De-identification: removing PII from the hospital discharge summaries. Our results showed that the ensemble model combined using the stacking Support Vector Machine (SVM) method on the three base-models with the best F1 scores achieved excellent results with a F1 score of 99.16% on the test set of our corpus. We also evaluated the robustness of our modelling component on the 2014 i2b2 de-identification dataset. Our ensemble model, which uses the token-level majority voting method on all six base-models, achieved the highest F1 score of 96.24% at strict entity matching and the highest F1 score of 98.64% at binary token-level matching compared to two state-of-the-art methods. The end-to-end framework provides a robust solution to de-identifying clinical narrative corpuses safely. It can easily be applied to any kind of clinical narrative documents. © 2022 The Author(s)
A51: S050 | B51: Chen B.; Jiang L.; Pan X.; Zhou G.; Sun A.; Li D. | C51: 2024 | D51: Exploring Emotion Trends in Product Reviews: A Multi-modal Analysis with Malicious Comment Filtering and User Privacy Protection | E51: Lecture Notes in Computer Science (including subseries Lecture Notes in Artificial Intelligence and Lecture Notes in Bioinformatics) | F51: Conference paper | G51: 10.1007/978-981-97-0942-7_19 | H51: Excluido | I51: E2 | J51: El problema es el análisis de sentimiento; las regex de privacidad son un paso menor. | K51: Excluido | L51: Comercio / reseñas | M51: General / documentos | N51: Inglés | O51: Inglés | P51: X | S51: X | W51: =IF(AND(P51="X",OR(R51="X",S51="X",T51="X")),"Sí","No") -> Sí | AL51: No | AM51: No | AN51: No | AO51: Reseñas de libros de Amazon | AP51: Exactitud 94,15 % en sentimiento | AQ51: Abstract | AR51: In this paper, we introduce an innovative approach that combines multi-modal sentiment analysis with mechanisms for safeguarding user information security. Our objective is to effectively combat harmful comments and precisely forecast trends in product sentiment. Initially, we detect and secure sensitive user information by implementing regular expressions to ensure user confidentiality and security. First, we apply statistical analysis and K-means++ algorithms to screen users who post malicious reviews. Next, we develop a novel multi-modal sentiment analysis and prediction model that incorporates the pre-trained BERT model and Swin Transformer model for feature extraction from comment text and image data. Furthermore, the expressive capability of image features is enhanced with the aid of the SENet model. We input the image features, improved by the SENet model, as well as the text features, extracted by the BERT model, into the Transformer model for fusion, and the classification probability is determined using the SoftMax function. We employ the Prophet method to combine sentiment indicators and time series features, which allows us to predict the upcoming sentiment trends of product reviews. The algorithm is implemented in the evaluation of the Amazon book review datasets and is compared to other algorithms such as Bert, yielding an accuracy of 94.15%. This study is of significant value for enabling real-time monitoring of product sentiment trends, filtering malicious reviews, and enhancing both product management and user experience. © The Author(s), under exclusive license to Springer Nature Singapore Pte Ltd. 2024.
A52: S051 | B52: Rout P.; Bansal D.; Satapathy P.; Reddy T.S.; Shivani S.; Kumari P.; Rao S.; Dahiya O.; Thakur T. | C52: 2026 | D52: AI-Driven Privacy Masking: A Context-Aware Hybrid Model for Multilingual and Unstructured Documents | E52: 2026 International Conference on Intelligent Systems in Engineering, Secured Systems and Cybersecurity, ICISESSC 2026 | F52: Conference paper | G52: 10.1109/ICISESSC68634.2026.11542816 | H52: Núcleo | I52: N | J52: Transformer más reglas para identificadores regionales; insiste en combinar reglas y aprendizaje por transferencia. | K52: Núcleo | L52: Documentos multilingües | M52: General / documentos | N52: Multilingüe | O52: Multilingüe | P52: X | S52: X | W52: =IF(AND(P52="X",OR(R52="X",S52="X",T52="X")),"Sí","No") -> Sí | AB52: X | AC52: X | AL52: No | AM52: No | AN52: No | AO52: Documentos (no detalla) | AP52: Supera a herramientas abiertas en P, R y enmascaramiento | AQ52: Abstract | AR52: The increasing volume of digital documents containing Personally Identifiable Information (PII) has increased the demand for automated privacy masking solutions that ensure adherence to emerging data protection regulations, including the General Data Protection Regulation (GDPR) and India's Digital Personal Data Protection (DPDP) Act. Intelligent, context-aware PII detection solutions are critical since manual redaction of sensitive data is costly, error-prone, and unworkable when scaled. Current Named Entity Recognition (NER) techniques are inadequate for unstructured document formats, multilingual documents, and ambiguous or domain-specific identifiers. In this research, we present a hybrid AI-based solution for document-level PII detection and redaction that blends transformer-based deep learning with rule-based reasoning for region-specific identifiers like Aadhaar, PAN, and IFSC codes, and other structured identifiers, showing superior precision, recall, and masking accuracy than current open-source technologies. This study provides an analysis of scalable document-privacy pipelines that are appropriate for corporations, government agencies, and educational institutions, emphasizing the need to combine rulebased enhancement with transfer learning for effective PII masking. © 2026 IEEE.
A53: S052 | B53: Yuan G.; Zhao X.; Li L.; Zhang S.; Wei S. | C53: 2024 | D53: Few-Shot Learning Sensitive Recognition Method Based on Prototypical Network | E53: Mathematics | F53: Article | G53: 10.3390/math12172791 | H53: Núcleo | I53: N | J53: Red prototípica para reconocer datos sensibles con pocos ejemplos. | K53: Núcleo | L53: Texto general | M53: General / documentos | N53: Chino (probable) | O53: Otra lengua | R53: X | S53: X | W53: =IF(AND(P53="X",OR(R53="X",S53="X",T53="X")),"Sí","No") -> No | AL53: No | AM53: No | AN53: No | AO53: Conjunto de prueba propio | AP53: P 84,8 %; R 85,8 %; F1 0,853 | AQ53: Abstract | AR53: Traditional machine learning-based entity extraction methods rely heavily on feature engineering by experts, and the generalization ability of the model is poor. Prototype networks, on the other hand, can effectively use a small amount of labeled data to train models while using category prototypes to enhance the generalization ability of the models. Therefore, this paper proposes a prototype network-based named entity recognition (NER) method, namely the FSPN-NER model, to solve the problem of difficult recognition of sensitive data in data-sparse text. The model utilizes the positional coding model (PCM) to pre-train the data and perform feature extraction, then computes the prototype vectors to achieve entity matching, and finally introduces a boundary detection module to enhance the performance of the prototype network in the named entity recognition task. The model in this paper is compared with LSTM, BiLSTM, CRF, Transformer and their combination models, and the experimental results on the test dataset show that the model outperforms the comparative models with an accuracy of 84.8%, a recall of 85.8% and an F1 value of 0.853. © 2024 by the authors.
A54: S053 | B54: Ali S.D. | C54: 2026 | D54: SecureLogX: A Java-Native, AI-Augmented Logging Framework for Privacy-Preserving, Parallel Log Processing in Enterprise Systems | E54: Conference Proceedings - IEEE SOUTHEASTCON | F54: Conference paper | G54: 10.1109/SoutheastCon63549.2026.11476327 | H54: Núcleo | I54: N | J54: Enmascara entidades en logs empresariales con un NER transformer en línea, con baja latencia. | K54: Núcleo | L54: Software / logs | M54: Software / secretos técnicos | N54: No indicado | O54: No indicado o no aplica | S54: X | W54: =IF(AND(P54="X",OR(R54="X",S54="X",T54="X")),"Sí","No") -> No | AL54: No | AM54: No | AN54: No | AO54: Logs JSON, XML y texto | AP54: Latencia | AQ54: Abstract | AR54: Enterprise logging systems must meet increasing demands for real-time privacy compliance under regulations such as HIPAA and GDPR while sustaining high throughput. This paper presents SecureLogX, an AI-powered Java logging framework for inline, privacy-preserving observability. SecureLogX integrates ONNX-based transformer inference with parallel and asynchronous log processing to enable adaptive masking of sensitive entities across JSON, XML, and text logs. The hybrid NER engine dynamically identifies personal identifiers without reliance on static regex rules. Experimental evaluation demonstrates low-latency performance suitable for distributed microservice environments. © 2026 IEEE.
A55: S054 | B55: Luo N.; Weng C.; Singh J.; Tan G.; Raykova M.; Piskac R. | C55: 2024 | D55: Privacy-Preserving Regular Expression Matching Using TNFA | E55: Lecture Notes in Computer Science (including subseries Lecture Notes in Artificial Intelligence and Lecture Notes in Bioinformatics) | F55: Conference paper | G55: 10.1007/978-3-031-70890-9_12 | H55: Excluido | I55: E2 | J55: Protocolos para evaluar regex de forma privada; no detecta información sensible. | K55: Excluido | L55: Criptografía | M55: Ciberseguridad u otro problema | N55: No aplica | O55: No indicado o no aplica | P55: X | W55: =IF(AND(P55="X",OR(R55="X",S55="X",T55="X")),"Sí","No") -> No | AL55: No | AM55: No | AN55: No | AO55: - | AP55: Complejidad y latencia | AQ55: Abstract | AR55: Regular expression (regex) is a powerful tool to efficiently search patterns in text strings. However, it is common when the regex and string are privately held by different parties who are unwilling to reveal sensitive information. In this work, we provide solutions for private regex pattern match. By exploiting the structure of Thompson nondeterministic automata, we design a regex match algorithm with O(mn) complexity where m and n are the length of the string and regex. It is oblivious to the input string and, hence, is friendly to private evaluation. We develop two 2-party regex matching protocols that take input a private string from one party and a private regex from another. The first protocol uses oblivious stack as a building block and reduces the communication complexity of the state-of-the-art secure regex protocols from O(mn2) to O(mnlogn). The second protocol is based on the oblivious transfer and shows better empirical results for short regex in low-latency networks. We also evaluated our protocols in the context of joint intrusion detection and DNA sequence search. The results indicate one more step toward the practicality of private regex pattern matching in real-world applications. © The Author(s), under exclusive license to Springer Nature Switzerland AG 2024.
A56: S055 | B56: Almeida A.; Shah S.; Khandor N.B.; Agarwal N. | C56: 2024 | D56: LEGAL AI: A Tool to help Lawyers Optimize their Performance | E56: 2024 International Conference on Electrical, Electronics and Computing Technologies, ICEECT 2024 | F56: Conference paper | G56: 10.1109/ICEECT61758.2024.10739264 | H56: Complementario | I56: C5 | J56: Herramienta general para abogados; la redacción de datos del cliente es una función secundaria. | K56: Excluido | L56: Legal | M56: Legal / policial | N56: No indicado | O56: No indicado o no aplica | R56: X | W56: =IF(AND(P56="X",OR(R56="X",S56="X",T56="X")),"Sí","No") -> No | AL56: No | AM56: No | AN56: No | AO56: - | AP56: - | AQ56: Abstract | AR56: The modern legal environment where quick changes are happening requires integrating advanced technologies to make legal professionals more efficient and effective. The purpose of this project is to propose "LegalAI,"which could solve some of the critical challenges legal software and hardware lawyers currently face, such as document analysis, language translation, and privacy. Legal AI's primary concern is the difficulty and time- intensive nature of reviewing extensive legal documents. By synthesizing and recomposing key points, Legal AI aids the lawyer in obtaining the most important content from lengthier texts as soon as possible. This increases experts' time and productivity. Moreover, the capabilities of legal AI include translation of the language to ensure free interaction among the lawyers from states. It will contribute to greater cohesion and collaboration within the legal cluster. There are several aspects related to the privacy of the client's sensitive information such as redaction. All of the abovementioned aspects contribute to the considerable opportunities of legal AI to improve the performance of the professionals. In general, legal Ai involves the integration of automated document summary, language translation, and privacy protection mechanisms for better performance of the lawyers. © 2024 IEEE.
A57: S056 | B57: Rahman M.N.; Ahmed S.; Wahab Z.; Uddin G.; Shahriyar R. | C57: 2026 | D57: IssueGuard: Real-Time Secret Leak Prevention Tool for GitHub Issue Reports | E57: FSE Companion 2026 - Proceedings of the 34th ACM International Conference on the Foundations of Software Engineering | F57: Conference paper | G57: 10.1145/3803437.3806406 | H57: Núcleo | I57: N | J57: Extensión que detecta secretos mientras el usuario escribe, con regex de candidatos y CodeBERT; base del criterio para CREDENTIAL / SECRET. | K57: Núcleo | L57: Software (GitHub) | M57: Software / secretos técnicos | N57: Inglés | O57: Inglés | P57: X | S57: X | W57: =IF(AND(P57="X",OR(R57="X",S57="X",T57="X")),"Sí","No") -> Sí | AG57: X | AL57: Sí | AM57: No | AN57: No | AO57: Benchmark de secretos en issues | AP57: F1 92,70 % | AQ57: Abstract y texto completo | AR57: GitHub and GitLab are widely used collaborative platforms whose issue-tracking systems contain large volumes of unstructured text, including logs, code snippets, and configuration examples. This creates a significant risk of accidental secret exposure, such as API keys and credentials, yet these platforms provide no mechanism to warn users before submission. We present IssueGuard, a tool for real-time detection and prevention of secret leaks in issue reports. Implemented as a Chrome extension, IssueGuard analyzes text as users type and combines regex-based candidate extraction with a fine-tuned CodeBERT model for contextual classification. This approach effectively separates real secrets from false positives and achieves an F1-score of 92.70% on a benchmark dataset, outperforming traditional regex-based scanners. IssueGuard integrates directly into the web interface and continuously analyzes the issue editor, presenting clear visual warnings to help users avoid submitting sensitive data. The source code is publicly available at https://github.com/disa-lab/IssueGuard, and a demonstration video is available at https://youtu.be/kvbWA8rr9cU. © 2026 Copyright held by the owner/author(s).
A58: S057 | B58: Huang Y.-Z.; Peng T.-C.; Lin H.-Y.; Sy E.; Chang Y.-C. | C58: 2025 | D58: Enhancing Automated De-identification of Pathology Text Notes Using Pre-trained Language Models | E58: Communications in Computer and Information Science | F58: Conference paper | G58: 10.1007/978-981-97-7966-6_2 | H58: Núcleo | I58: N | J58: T5 ajustado con regex y la librería Pycountry para reducir falsos positivos. | K58: Núcleo | L58: Clínico | M58: Salud / clínico | N58: Inglés | O58: Inglés | P58: X | T58: X | W58: =IF(AND(P58="X",OR(R58="X",S58="X",T58="X")),"Sí","No") -> Sí | AE58: X | AL58: No | AM58: No | AN58: No | AO58: Notas de patología | AP58: F1 macro de 0,779 a 0,919 | AQ58: Abstract | AR58: With the recent advancements in artificial intelligence (AI), particularly the surge in large language models (LLMs) led by industry giants such as OpenAI, Microsoft, and Google, a new era in clinical medicine and digital health has been ushered in. These advancements, transformative as they are, introduce significant privacy concerns, particularly in the healthcare sector, which heavily relies on Electronic Health Records notes (EHRs) text notes. Our research directly addresses these privacy challenges by enhancing the T5-Efficient-BASE-DL2 model for the de-identification of patient data. We fine-tuned the T5 model with specific hyperparameter adjustments and implemented exact match evaluations to significantly reduce false positives and improve the accuracy of entity recognition, particularly for sensitive information processing. This was achieved using regular expressions and the Pycountry library. Our enhancements resulted in a notable improvement in the model’s performance, with a 14% increase in the macro-average F1-score for Task 1, rising from 0.7787 to 0.9187, and a 30% improvement for Task 2, from 0.4871 to 0.79. These advancements not only enhance the security and efficiency of healthcare information management but also uphold the integrity of individual privacy and facilitate the safe sharing of data for research purposes without compromising confidentiality. Our research lays the groundwork for future developments in improving rule-based methodologies and expanding datasets, aiming to further integrate machine learning with linguistic rules for more effective data privacy solutions in healthcare. © The Author(s), under exclusive license to Springer Nature Singapore Pte Ltd. 2025.
A59: S058 | B59: Abbasi W. | C59: 2023 | D59: Privacy-Preserving Speaker Verification and Speech Recognition | E59: Lecture Notes in Computer Science (including subseries Lecture Notes in Artificial Intelligence and Lecture Notes in Bioinformatics) | F59: Conference paper | G59: 10.1007/978-3-031-25467-3_7 | H59: Complementario | I59: C3 | J59: Anonimiza la transcripción con NER antes de enviarla a terceros; la entrada es audio. | K59: Excluido | L59: Voz | M59: Voz o imagen | N59: Inglés | O59: Inglés | R59: X | V59: X | W59: =IF(AND(P59="X",OR(R59="X",S59="X",T59="X")),"Sí","No") -> No | AL59: Sí | AM59: Sí | AN59: No | AO59: LibriSpeech | AP59: Exactitud y similitud con el resultado sin privacidad | AQ59: Abstract | AR59: This paper proposes an approach to speaker verification and speech recognition in environments that require authentication and privacy protection, while accuracy and data utility must remain high. Our methodology aims at protecting audio files and users’ identities through the use of encryption and hashing algorithms, while at the same time providing accurate speaker’s identity prediction. In addition, for speech recognition, we introduce a mechanism to anonymize the resulting transcript of the recognized spoken language using the Named Entity Recognition method by removing sensitive entities from the text according to the user’s preferences. Furthermore, a privacy-preserving version of the original audio is obtained by performing a text-to-speech translation of the anonymized transcript, which together, the anonymous audio and transcript can be transmitted to third parties or service providers without violating privacy restrictions. The proposed methodology has been validated with a set of experiments on a well-known audio dataset, the Librispeech dataset. A type of Time Delay Neural Networks, ECAPA-TDNN was used for speaker verification, Deep Speech as a type of Recurrent Neural Networks was used for speech recognition, NER for entity recognition, cryptography and hashing for privacy protection. The results demonstrate the validity of our approach to protecting the privacy of user data and biometric information while simultaneously performing data analysis with a high degree of accuracy and similarity with the results obtained with no privacy mechanisms in place, also considering the use of several privacy mechanisms. © 2023, Springer Nature Switzerland AG.
A60: S059 | B60: Gunay M.; Keles B.; Hizlan R. | C60: 2026 | D60: Large language models-in-the-loop: Leveraging expert small artificial intelligence models for multilingual anonymization and de-identification of protected health information | E60: Artificial Intelligence in Health | F60: Article | G60: 10.36922/AIH025120021 | H60: Núcleo | I60: N | J60: Modelos NER pequeños entrenados con LLM en el ciclo; superan a GPT-4o y evitan enviar datos a una API. | K60: Núcleo | L60: Clínico | M60: Salud / clínico | N60: Multilingüe (incluye español) | O60: Español (solo o con otras lenguas) | S60: X | T60: X | W60: =IF(AND(P60="X",OR(R60="X",S60="X",T60="X")),"Sí","No") -> No | AL60: No | AM60: No | AN60: No | AO60: Textos clínicos en ocho idiomas | AP60: F1 macro 0,922–0,963; 0,957 en español | AQ60: Abstract | AR60: The rise of chronic diseases and pandemics, such as COVID-19 has emphasized the need for effective patient data processing while ensuring privacy through anonymization and de-identification of protected health information. Anonymized data facilitates research without compromising patient confidentiality. This paper introduces expert small artificial intelligence (AI) models developed using the large language model (LLM)-in-the-loop methodology to meet the demand for domain-specific de-identification of named entity recognition (NER) models. These models overcome the privacy risks associated with LLMs used through application programming interfaces by eliminating the need to transmit or store sensitive data. More importantly, they consistently outperform LLMs in de-identification tasks, offering superior performance and reliability. Our de-identification NER models, developed in eight languages—English, German, Italian, French, Romanian, Turkish, Spanish, and Arabic—achieved F1-macro score averages of 0.931, 0.960, 0.955, 0.937, 0.930, 0.963, 0.957, and 0.922, respectively. These results establish our de-identification NER models as the most accurate healthcare anonymization solutions, surpassing existing small models and even general-purpose LLMs, such as GPT-4o. While Part I of this series introduced the LLM-in-the-loop methodology for biomedical document translation, this second paper showcases its success in developing cost-effective expert small NER models in de-identification tasks. Our findings lay the groundwork for future healthcare AI innovations, including biomedical entity and relation extraction, demonstrating the value of specialized models for domain-specific challenges. © 2025 Author(s).
A61: S060 | B61: Kamal A.H.; Kayem A.V.D.M. | C61: 2026 | D61: Classifying Public and Private Documents Using Context-Based Predictions | E61: Lecture Notes in Computer Science | F61: Conference paper | G61: 10.1007/978-3-032-02049-9_29 | H61: Complementario | I61: C4 | J61: Clasifica documentos como públicos o privados según la información sensible que contienen; sensibilidad por documento. | K61: Complementario | L61: Correo y redes sociales | M61: General / documentos | N61: Inglés | O61: Inglés | R61: X | S61: X | W61: =IF(AND(P61="X",OR(R61="X",S61="X",T61="X")),"Sí","No") -> No | AL61: No | AM61: No | AN61: No | AO61: Correos de Enron y tuits | AP61: Exactitud 100 % (públicos); recall 0,98 (privados) | AQ61: Abstract | AR61: Unstructured data, such as textual data, is prevalent on digital platforms such as social media, with users posting content that sometimes includes sensitive information. For instance, in March of 2025, a press story by journalist Jeffrey Goldberg indicated that secret Trump administration plans for an air strike on Yemen had inadvertently been leaked to him (U.S. national-security leaders included me in a group chat aboutupcoming military strikes in Yemen...). Despite regulations, and the existence of access control policies data leaks such as this are persistent. One of the reasons for this is that contextually analysing unstructured data to determine whether or not sensitive information exists therein, is a challenging problem. Existing approaches identify individual elements of sensitive information such as Personally Identifiable Information (PII), but few works look at the issue of document sensitivity based on the occurrence of sensitive information. In this paper we propose a novel approach to classifying documents as either public or private, based on the occurrence of, and contextual interpretation of sensitive information within the document. We employ an ensemble model composed of transformer-encoder models and standard machine learning models to support the classification process. Our empirical study, conducted on a curated dataset composed of ENRON emails and Tweets of U.S. Congress members, indicates that the Random Forest algorithm when combined with the BERT model classifies all public documents correctly (i.e. 100% accuracy), and achieves a 0.98 recall score for private documents. © The Author(s), under exclusive license to Springer Nature Switzerland AG 2026.
A62: S061 | B62: Sivaraman A.; Furniturewala M.; Gayathri P. | C62: 2023 | D62: Detecting and Fixing SQL Injection and Cross-Site Scripting Vulnerabilities in Web Applications | E62: 2023 Innovations in Power and Advanced Computing Technologies, i-PACT 2023 | F62: Conference paper | G62: 10.1109/I-PACT58649.2023.10434879 | H62: Excluido | I62: E2 | J62: Detecta vulnerabilidades SQL injection y XSS; no trata información sensible en texto. | K62: Excluido | L62: Seguridad web | M62: Ciberseguridad u otro problema | N62: No aplica | O62: No indicado o no aplica | P62: X | R62: X | W62: =IF(AND(P62="X",OR(R62="X",S62="X",T62="X")),"Sí","No") -> Sí | AL62: No | AM62: No | AN62: No | AO62: Código PHP | AP62: - | AQ62: Abstract | AR62: More people have access to the internet than ever before. This has prompted many organizations to develop web-based applications that users can use online to interact with the organization. Poorly written code for web applications, especially SQL queries can be exploited to gain unauthorized access to sensitive data and web servers. It is not possible to manually scroll through the codebase to detect parts of code that would make the application vulnerable to attacks. Thus, machine learning and natural language processing-based solutions would help detect such queries either based on their patterns or signatures or through training via previous attack datasets. This paper aims to propose a novel methodology to detect SQL injection vulnerable queries and Cross-Site Scripting (XSS) attacks using pattern matching and NLP techniques and rewrite or in other words correct the vulnerable parts of code to prevent such attacks. Overall, this paper is used to identify vulnerable parts of code in a given client-side PHP web application, detect if the vulnerability belongs to a particular attack type and finally correct the vulnerable section of the code by providing recommendations based on standard prevention techniques for the corresponding attacks. © 2023 IEEE.
A63: S062 | B63: Tobia G.P.; Patarnello S.; Masciocchi C.; Nero C.; Passarotti M.C.; Moretti G.; Marchetti A.; Arcuri G.; Lilli L. | C63: 2025 | D63: Privacy in Italian Clinical Reports: A NLP-Based Anonymization Approach | E63: Proceedings - 2025 IEEE 13th International Conference on Healthcare Informatics, ICHI 2025 | F63: Conference paper | G63: 10.1109/ICHI64645.2025.00077 | H63: Núcleo | I63: N | J63: BERT ajustado para PHI en italiano; discute el desbalance de clases. | K63: Núcleo | L63: Clínico | M63: Salud / clínico | N63: Italiano | O63: Otra lengua | S63: X | W63: =IF(AND(P63="X",OR(R63="X",S63="X",T63="X")),"Sí","No") -> No | AL63: No | AM63: No | AN63: No | AO63: 1.000 cartas de alta y 100 sintéticas | AP63: No reporta valores en el abstract | AQ63: Abstract | AR63: The sharing of data is of significant importance for the advancement of scientific and technological knowledge. However, legislation such as the General Data Protection Regulation (GDPR) in Europe and the Health Insurance Portability and Accountability Act (HIPAA) in the United States implies significant restrictions on the dissemination of personal data within the healthcare sector. This has led to the development of reliable and automated methods for the anonymization of clinical documents, becoming a key area of research.This study presents a Natural Language Processing (NLP) approach to anonymize Italian clinical reports, focusing on protecting patient privacy by identifying and masking personally identifiable information. The research employs BERT-based Named Entity Recognition models, fine-tuning them on the healthcare-specific domain. The dataset, consisting of 1000 discharge letters from the Gemelli Hospital of Rome and 100 synthetically generated reports, was annotated to include critical protected health information (PHI) categories. The study compares different tagging schemes and loss functions, addressing class imbalance. The results demonstrate that a pre-trained model designed to recognize personal identifiable information in general texts can be effectively adapted and specialized to detect PHI in clinical reports in order to anonymize them.This work underscores the challenges of handling unbalanced datasets, the over-representation of non-PHI tokens, and interclass ambiguities. This research contributes to the development of a novel transformer-based model specialized in Italian clinical text, providing a framework for clinical text anonymization, ensuring compliance with privacy standards like GDPR while preserving the utility of data for research. © 2025 IEEE.
A64: S063 | B64: Fakhfakh E.; Charfeddine M.; Tarhouni N.; Guettat M.A. | C64: 2024 | D64: Combining TF-IDF, V-GAN, and XGB to Improve Next-Generation Web Application Firewalls' Ability to Detect SQL Injection Attacks | E64: Proceedings of IEEE/ACS International Conference on Computer Systems and Applications, AICCSA | F64: Conference paper | G64: 10.1109/AICCSA63423.2024.10912540 | H64: Excluido | I64: E2 | J64: Detecta ataques de SQL injection; no trata información sensible en texto. | K64: Excluido | L64: Seguridad web | M64: Ciberseguridad u otro problema | N64: No aplica | O64: No indicado o no aplica | P64: X | R64: X | W64: =IF(AND(P64="X",OR(R64="X",S64="X",T64="X")),"Sí","No") -> Sí | AL64: No | AM64: No | AN64: No | AO64: Tráfico de red y consultas SQL | AP64: Exactitud 99,95 % | AQ64: Abstract | AR64: SQL injection attacks are one of the most devastating vulnerabilities on the web, which can be used to leak sensitive information, gain unauthorized access, and result in financial losses. We utilized five distinct Machine Learning (ML) and Deep Learning (DL) algorithms to detect SQL injection attacks. We extracted features from network traffic and SQL queries through tokenization and regular expressions. Our findings show that combining the Term Frequency-Inverse Document Frequency (TF-IDF), Vanilla Generative Adversarial Network (VGAN), and eXtreme Gradient Boosting (XGB) models resulted in remarkably high performance metrics, including 99.95 % accuracy, 99.92 % precision, 99.97 % recall, and a 99.95 % F1-score. The results not only show the combination's effectiveness but also emphasize the importance of using machine learning techniques to detect SQL injection attacks to improve real-world cybersecurity applications significantly. © 2024 IEEE.
A65: S064 | B65: Juez-Hernandez R.; Quijano-Sánchez L.; Liberatore F.; Gómez J. | C65: 2023 | D65: AGORA: An intelligent system for the anonymization, information extraction and automatic mapping of sensitive documents | E65: Applied Soft Computing | F65: Article | G65: 10.1016/j.asoc.2023.110540 | H65: Núcleo | I65: N | J65: AGORA anonimiza documentos de instituciones públicas españolas; antecedente en español. | K65: Núcleo | L65: Policial y clínico | M65: Legal / policial | N65: Español | O65: Español (solo o con otras lenguas) | R65: X | S65: X | W65: =IF(AND(P65="X",OR(R65="X",S65="X",T65="X")),"Sí","No") -> No | AE65: X | AL65: No | AM65: No | AN65: No | AO65: Informes policiales y médicos | AP65: Comparación de configuraciones NER | AQ65: Abstract | AR65: Public institutions, such as law enforcement agencies or health centers, have a vast volume of unstructured text documents, e.g. police reports. Currently, before this data can be shared (e.g. with research institutions), it must go through a lengthy and costly human anonymization procedure. This paper addresses this issue by presenting AGORA, a cutting-edge tool that automatically identifies key entities and anonymizes sensitive data in text documents. AGORA has been developed in partnership with the Spanish National Office Against Hate Crimes and validated in the police and medical domains. This tool allows to export both anonymized texts and identified entities to structured files, thus, simplifying its exploitation for analysis purposes. Also, AGORA is capable of plotting the location entities identified in the documents, as well as obtaining and displaying relevant information from their geographical surroundings. Thus, it simplifies the task of generating comprehensive datasets for subsequent data analysis or predictive tasks. Its main goal is to foster cooperation between public institutions and research centers by easing document sharing as well as serving as a foundation for addressing succeeding phases in data science. The paper conducts a comprehensive assessment of the literature on Named Entity Recognition methodologies and technologies. Followed by extensive computational experiments to identify the best configuration for the NER models embedded in AGORA which include both successful state-of-the-art model setups and novelly proposed ones. Finally, the methodology, conclusions and software provided can be easily reused in similar application scenarios. © 2023 The Author(s)
A66: S065 | B66: Sheela S.; Suvarna M.D.; Kusuma M.; Chaithrashree S.; Raksha P. | C66: 2025 | D66: Blockchain - Enabled Hybrid Approach for Reliable Detection and Privacy Preservation of PII | E66: 3rd International Conference on Emerging Computation and Information Technologies, ICECIT 2025 - Book of Abstracts | F66: Conference paper | G66: 10.1109/ICECIT67774.2025.11450940 | H66: Núcleo | I66: N | J66: Regex, spaCy y BERT combinados, con OCR para documentos escaneados; versión previa del estudio S046. | K66: Núcleo | L66: Documentos de identidad | M66: Gobierno / identidad | N66: Inglés (India) | O66: Inglés | P66: X | R66: X | S66: X | V66: X | W66: =IF(AND(P66="X",OR(R66="X",S66="X",T66="X")),"Sí","No") -> Sí | AL66: No | AM66: No | AN66: No | AO66: Conjunto sintético de PII india | AP66: Mejor que los modelos solos (sin valores en el abstract) | AQ66: Abstract | AR66: In this era of digital services, security of Personally Identifiable Information (PII) is mandatory to prevent data breaches and identity theft. This paper presents a hybrid PII detection and secure verification system integrating rule-based regular expressions, transformer-based spaCy NLP, and BERT models that are balanced between accuracy and context correctness for various document formats. The hybrid method leverages the advantages of the two methods, leading to improved detection performance than standalone models, as demonstrated on a synthetic Indian PII dataset. For privacy management, a double hashing method with a blockchain support using SHA256 ensures tamper-proof, immovable storage of PII fingerprints without revealing raw data. An. OTP-based authentication secures user entry, and scanned PDFs and images are processed by the system via OCR to identify and validate PII. The hybrid model offers a. robust and privacy-enhancing solution to identity authentication. that covers scalability, interpretability, and security loopholes. of current methods. © 2025 IEEE.
A67: S066 | B67: Dilmaç F.; Alpkocak A. | C67: 2026 | D67: De-Identification of Electronic Health Records Using Deep Learning and Transformers | E67: Applied Sciences (Switzerland) | F67: Article | G67: 10.3390/app16041692 | H67: Núcleo | I67: N | J67: Compara BiLSTM y BiLSTM-CRF con transformers ajustados; los transformers superan a los modelos secuenciales. | K67: Núcleo | L67: Clínico | M67: Salud / clínico | N67: Turco | O67: Otra lengua | R67: X | S67: X | W67: =IF(AND(P67="X",OR(R67="X",S67="X",T67="X")),"Sí","No") -> No | AL67: No | AM67: No | AN67: No | AO67: Historias clínicas turcas anotadas (publicadas) | AP67: F1 macro 92,20 % (transformers); 83,00 % (BiLSTM-CRF) | AQ67: Abstract | AR67: Adoption of electronic health records (EHRs) has significantly advanced healthcare by enabling extensive data storage and analysis for clinical decisions and research. However, sensitive personally identifiable information (PII) within EHRs presents major challenges concerning patient privacy, data security, and regulatory compliance. Effective automated de-identification techniques for detecting and removing protected health information (PHI) are thus essential. This study presents one of the first focused studies on Turkish EHR de-identification, comparing traditional sequence-based neural architectures with advanced transformer-based large language models (LLMs) for PHI detection. We introduce and publicly release a manually annotated benchmark dataset of TEHRs, covering diverse PHI types, supporting further research in Turkish clinical text. Two methodologies were evaluated: bidirectional long short-term memory (BiLSTM) models (with and without Conditional Random Fields (CRFs)) and six fine-tuned pre-trained LLMs. Experiments demonstrated the superior performance of transformer-based LLMs, achieving a macro F1 score of 92.20%, significantly outperforming traditional methods. Among sequence-based models, BiLSTM + CRF attained an 83.00% F1 score, exceeding the baseline BiLSTM 78.40%. Results highlight the potential of transformer-based models for privacy-preserving Turkish clinical text and underscore the importance of annotated benchmark datasets. © 2026 by the authors.
A68: S067 | B68: Kondru V.S.A.; Kasukurthi V.R. | C68: 2026 | D68: DLGNet: A Deep Learning and Generative Framework for Privacy-preserving PII De-identification with Semantic Verification | E68: International Journal of Intelligent Engineering and Systems | F68: Article | G68: 10.22266/ijies2026.0930.53 | H68: Núcleo | I68: N | J68: DeBERTa más verificación semántica con un LLM y reemplazo por tipo; reporta una métrica orientada al recall, como el F2 de este trabajo. | K68: Núcleo | L68: Salud, educación y empresa | M68: General / documentos | N68: No indicado | O68: No indicado o no aplica | P68: X | S68: X | T68: X | W68: =IF(AND(P68="X",OR(R68="X",S68="X",T68="X")),"Sí","No") -> Sí | AL68: No | AM68: Sí | AN68: No | AO68: No indicado | AP68: P 90,3 %; R 94,7 %; F1 92,4 %; Fβ (β = 5) 94,52 % | AQ68: Abstract | AR68: The rapid growth of unstructured textual data in domains such as healthcare, education, and enterprise systems has increased the risk of inadvertent exposure of Personally Identifiable Information (PII). Effective de-identification is essential to enable secure data sharing while preserving privacy and regulatory compliance. Existing approaches, including rule-based and deep learning-based Named Entity Recognition (NER) methods, primarily focus on detection and often lack contextual validation and robust replacement mechanisms, leading to information loss or residual privacy risks. This work proposes DLGNet, a pipeline-based integrated framework PII de-identification framework that integrates DeBERTa-based token-level detection, LLM-based semantic verification, and type-aware replacement. A BIO-tagged DeBERTa model identifies candidate PII spans, which are refined using a TinyLlama-based semantic verification module for contextual validation. Detected entities are then replaced using a hybrid generative and rule-based strategy to ensure irreversible transformation while preserving textual coherence. Experimental results demonstrate strong recall-oriented performance, achieving precision of 90.3%, recall of 94.7%, F1-score of 92.4%, and Fβ-score (β = 5) of 94.52%. Utility evaluation shows a length ratio of 0.96 and token overlap of 0.73, indicating effective preservation of textual structure and semantics. The proposed framework provides a unified and practical solution for privacy-preserving text processing by jointly improving detection accuracy, contextual reliability, and data utility. This article is licensed under a Creative Commons Attribution-ShareAlike 4.0 International License. License details: https://creativecommons.org/licenses/by-sa/4.0/
A69: S068 | B69: Deußer T.; Hahnbück M.; Uelwer T.; Zhao C.; Bauckhage C.; Sifa R. | C69: 2025 | D69: Resource-Efficient Anonymization of Textual Data via Knowledge Distillation from Large Language Models | E69: Proceedings - International Conference on Computational Linguistics, COLING | F69: Conference paper | H69: Núcleo | I69: N | J69: Destila un LLM en un NER pequeño con regex para anonimizar sin enviar datos a una API. | K69: Núcleo | L69: General | M69: General / documentos | N69: No indicado | O69: No indicado o no aplica | P69: X | S69: X | T69: X | W69: =IF(AND(P69="X",OR(R69="X",S69="X",T69="X")),"Sí","No") -> Sí | AL69: No | AM69: No | AN69: No | AO69: No indicado | AP69: No reporta valores en el abstract | AQ69: Abstract | AR69: Protecting personal and sensitive information in textual data is increasingly crucial, especially when leveraging large language models (LLMs) that may pose privacy risks due to their API-based access. We introduce a novel approach and pipeline for anonymizing text across arbitrary domains without the need for manually labeled data or extensive computational resources. Our method employs knowledge distillation from LLMs into smaller encoder-only models via named entity recognition (NER) coupled with regular expressions to create a lightweight model capable of effective anonymization while preserving the semantic and contextual integrity of the data. This reduces computational overhead, enabling deployment on less powerful servers or even personal computing devices. Our findings suggest that knowledge distillation offers a scalable, resource-efficient pathway for anonymization, balancing privacy preservation with model performance and computational efficiency. ©2025 Association for Computational Linguistics.
A70: S069 | B70: Bang G.; Kim D.; Kim D.; Min M. | C70: 2027 | D70: Adaptive PII Detection via Evolutionary Orchestration and Multi-agent Debate | E70: Lecture Notes in Computer Science | F70: Conference paper | G70: 10.1007/978-981-92-1947-6_42 | H70: Núcleo | I70: N | J70: Sistema multiagente de LLM que se adapta a esquemas de PII distintos; usa AI4Privacy, como este trabajo. | K70: Núcleo | L70: General | M70: General / documentos | N70: Inglés | O70: Inglés | T70: X | W70: =IF(AND(P70="X",OR(R70="X",S70="X",T70="X")),"Sí","No") -> No | AL70: No | AM70: No | AN70: No | AO70: Nemotron-PII, AI4Privacy (pii-masking-200k y open-pii-masking-500k) | AP70: Desempeño competitivo en cero ejemplos | AQ70: Abstract | AR70: The definition of Personally Identifiable Information (PII) is fluid across legal jurisdictions and domain-specific schemas. Consequently, static Named Entity Recognition (NER) models often become brittle on heterogeneous datasets, while monolithic prompts suffer from attention degradation and hallucination when extracting extensive entity taxonomies. In this work, we propose a novel framework that reframes PII detection as a dynamic alignment problem rather than a static classification task. Our system features a Schema-Agnostic Orchestrator that dynamically decomposes target labels into semantic clusters, coupled with an Evolutionary Prompt Optimizer that automates the refinement of agent instructions using k-shot feedback. Furthermore, we integrate an uncertainty-aware debate protocol to resolve inter-agent conflicts through deliberative reasoning. Experiments on Nemotron-PII, AI4Privacy benchmarks (pii-masking-200k and open-pii-masking-500k) demonstrate that our adaptive system achieves competitive or superior performance against larger static baselines despite its smaller parameter footprint, establishing a new state-of-the-art in zero-shot PII adaptation. © The Author(s), under exclusive license to Springer Nature Singapore Pte Ltd. 2027.
A71: S070 | B71: Chandrashekhar P.S.; Manoj B.V.; Prakash J.S.; Laxman N.M.; Ismail S.A.; Prakash B.V. | C71: 2026 | D71: RedactSafe: Blockchain-Based PII Protection for Legal Audits | E71: Communications in Computer and Information Science | F71: Conference paper | G71: 10.1007/978-3-032-20907-8_37 | H71: Núcleo | I71: N | J71: Reglas, ML y OCR para redactar PII en auditorías legales, con almacenamiento en blockchain. | K71: Núcleo | L71: Legal / auditoría | M71: Legal / policial | N71: No indicado | O71: No indicado o no aplica | P71: X | R71: X | V71: X | W71: =IF(AND(P71="X",OR(R71="X",S71="X",T71="X")),"Sí","No") -> Sí | AL71: No | AM71: No | AN71: No | AO71: Documentos estructurados y no estructurados | AP71: Recall y precisión altos (sin valores) | AQ71: Abstract | AR71: Secure handling of Personally Identifiable Information (PII) in document exchange is critical with the advent of the digital age for data privacy as well as regulatory compliance. RedactSafe is an end-to-end framework that carries out automated detection, redaction, and secure storage of PII with the help of state-of-the-art Natural Language Processing methods like Optical Character Recognition (OCR) and Named Entity Recognition (NER). The system integrates rule based approaches with machine learning algorithms to identify sensitive data in both structured and unstructured documents effectively. Identified PII is then redacted and saved on the InterPlanetary File System (IPFS), while integrity and access history are recorded immutably using Ethereum smart contracts. A blended access control system, combining Attribute-Based Access Control (ABAC) and Role-Based Access Control (RBAC), restricts the ability of unauthorized users to view complete documents, with each request logged on-chain for auditing. In Experimental results, its is observed that there is high recall and precision in detecting PII, providing its effectiveness in maintaining documents confidential while remaining easy to use. The novelty of this work lies in its integrated approachmerging PII detection, redaction, audits logs and dynamic access. In sensitive environment, RedactSafe gives a scalable, privacy-protecting, and decentralized approach to secure document workflows. © The Author(s), under exclusive license to Springer Nature Switzerland AG 2026.
A72: S071 | B72: Sundrelingam V.; Parimoo S.; Pogacar F.; Koppula R.; Shin S.; Pou-Prom C.; Roberts S.B.; Verma A.A.; Razak F. | C72: 2025 | D72: pyDeid: an improved, fast, flexible, and generalizable rule-based approach for deidentification of free-text medical records | E72: JAMIA Open | F72: Article | G72: 10.1093/jamiaopen/ooae152 | H72: Núcleo | I72: N | J72: Desidentificación basada en regex y listas, con NER opcional; muestra el equilibrio entre desempeño y velocidad. | K72: Núcleo | L72: Clínico | M72: Salud / clínico | N72: Inglés | O72: Inglés | P72: X | Q72: X | R72: X | W72: =IF(AND(P72="X",OR(R72="X",S72="X",T72="X")),"Sí","No") -> Sí | X72: X | AL72: No | AM72: No | AN72: No | AO72: 700 notas canadienses, n2c2 y notas sintéticas | AP72: F1 0,904; 0,48 s por nota | AQ72: Abstract y texto completo | AR72: Objectives: Deidentification of personally identifiable information in free-text clinical data is fundamental to making these data broadly available for research. However, there exist gaps in the deidentification landscape with regard to the functionality and flexibility of extant tools, as well as suboptimal tradeoffs between deidentification accuracy and speed. To address these gaps and tradeoffs, we develop a new Python-based deidentification software, pyDeid. Materials and Methods: pyDeid uses a combination of regular expression-based rules, fixed exclusion lists and inclusion lists to deidentify free-text data. Additional configurations of pyDeid include optional named entity recognition and custom name lists. We measure its deidentification performance and speed on 700 admission notes from a Canadian hospital, the publicly available n2c2 benchmark dataset of American discharge notes, as well as a synthetic dataset of artificial intelligence (AI) generated admission notes. We also compare its performance with the Physionet De-identification Software and the popular open-source Philter tool. Results: Different configurations of pyDeid outperformed other tools on various metrics, with a “best” accuracy value of 0.988, best precision of 0.889, best recall of 0.950, and best F1 score of 0.904. All configurations of pyDeid were significantly faster than Philter and Physionet Deidentification Software, with the fastest deidentification speed of 0.48 s per note. Discussion and Conclusions: pyDeid allows the flexibility to prioritize between performance and speed, as well as precision and recall, while addressing some of the gaps in functionality left by other tools. pyDeid is also generalizable to domains outside of clinical data and can be further customized for specific contexts or for particular workflows. © The Author(s) 2025.
A73: S072 | B73: Choudhary S.; Sreya C.K.; Shivani U.; Jayanth; Kumar S.; Dipesh | C73: 2025 | D73: RE-DACT: Differential Privacy and Redaction Framework for Sensitive Data in Diverse Formats | E73: ICRTEECT 2025 - 2nd International Conference on Recent Trends in Electrical, Electronics and Computing Technologies | F73: Conference paper | G73: 10.1109/ICRTEECT67512.2025.11448648 | H73: Núcleo | I73: N | J73: NER de spaCy con políticas de enmascaramiento configurables y privacidad diferencial para datos tabulares. | K73: Complementario | L73: Documentos y datos tabulares | M73: General / documentos | N73: No indicado | O73: No indicado o no aplica | R73: X | V73: X | W73: =IF(AND(P73="X",OR(R73="X",S73="X",T73="X")),"Sí","No") -> No | X73: X | Y73: X | Z73: X | AD73: X | AF73: X | AL73: No | AM73: Sí | AN73: No | AO73: CSV y documentos de texto | AP73: No reporta valores en el abstract | AQ73: Abstract | AR73: Redacting sensitive data is vital for protecting privacy, particularly as organizations grow more dependent on sharing, analyzing, and storing information. Neglecting proper redaction can cause major legal, moral, and security issues. In this paper we present RE-DACT, a privacy-preserving framework for redacting and anonymizing sensitive data in both structured (e.g. csv files) and unstructured (e.g. text documents) formats. REDACT combines cutting-edge ML and NLP methodology for achieving data privacy while preserving data utility. For the structured data, we use the PATE-GAN model to generate synthetic datasets which preserve the statistical properties of the original data and while guaranteeing differential privacy. For raw text, it leverages a spaCy-based NER pipeline to extract sensitive entities such as names, dates, organizations and contact details and redact them via configurable masking policies. The framework also preserves the original document layout and formatting to ensure the readability and context, supports fast batch processing for large scale data and could be deployed both in cloud and on-premises. Extensive evaluation results show that RE-DACT achieves highly competitive performance for automatically redacting sensitive information while maintaining data utility and compliance with strict privacy requirements (e.g., GDPR, HIPAA, and CCPA). Our results shows that RE-DACT is a scalable, secure, resilient, and regulatory-compliant answer to contemporary data privacy and overlay matching, and stands as a promising solution for entities having to reconcile data utility with privacy compliance. © 2025 IEEE.
A74: S073 | B74: Benedetto I.; Koudounas A.; Vaiani L.; Pastor E.; Cagliero L.; Tarasconi F.; Baralis E. | C74: 2025 | D74: Boosting court judgment prediction and explanation using legal entities | E74: Artificial Intelligence and Law | F74: Article | G74: 10.1007/s10506-024-09397-8 | H74: Excluido | I74: E2 | J74: El objetivo es predecir y explicar fallos judiciales; el enmascaramiento de entidades es auxiliar. | K74: Excluido | L74: Legal | M74: Legal / policial | N74: Inglés | O74: Inglés | S74: X | T74: X | W74: =IF(AND(P74="X",OR(R74="X",S74="X",T74="X")),"Sí","No") -> No | AL74: No | AM74: No | AN74: No | AO74: Fallos judiciales de la India | AP74: Desempeño de predicción de fallos | AQ74: Abstract | AR74: The automatic prediction of court case judgments using Deep Learning and Natural Language Processing is challenged by the variety of norms and regulations, the inherent complexity of the forensic language, and the length of legal judgments. Although state-of-the-art transformer-based architectures and Large Language Models (LLMs) are pre-trained on large-scale datasets, the underlying model reasoning is not transparent to the legal expert. This paper jointly addresses court judgment prediction and explanation by not only predicting the judgment but also providing legal experts with sentence-based explanations. To boost the performance of both tasks we leverage a legal named entity recognition step, which automatically annotates documents with meaningful domain-specific entity tags and masks the corresponding fine-grained descriptions. In such a way, transformer-based architectures and Large Language Models can attend to in-domain entity-related information in the inference process while neglecting irrelevant details. Furthermore, the explainer can boost the relevance of entity-enriched sentences while limiting the diffusion of potentially sensitive information. We also explore the use of in-context learning and lightweight fine-tuning to tailor LLMs to the legal language style and the downstream prediction and explanation tasks. The results obtained on a benchmark dataset from the Indian judicial system show the superior performance of entity-aware approaches to both judgment prediction and explanation. © The Author(s), under exclusive licence to Springer Nature B.V. 2024.
A75: S074 | B75: Raffetseder D.; Weilguny C.; Haidinger P.; Pichler H.-P.; Narzt W. | C75: 2025 | D75: Beyond the Hype: Assessing Limitations of Large Language Models in Support Ticket Anonymization | E75: Lecture Notes in Computer Science | F75: Conference paper | G75: 10.1007/978-3-031-93418-6_21 | H75: Núcleo | I75: N | J75: Compara LLM con una solución basada en transformers para anonimizar tickets; los LLM rinden peor en casos reales. | K75: Núcleo | L75: Soporte técnico / empresarial | M75: Empresarial | N75: No indicado | O75: No indicado o no aplica | S75: X | T75: X | W75: =IF(AND(P75="X",OR(R75="X",S75="X",T75="X")),"Sí","No") -> No | AL75: No | AM75: No | AN75: No | AO75: Tickets de soporte | AP75: Desempeño de anonimización | AQ75: Abstract | AR75: In the evolving landscape of Natural Language Processing (NLP), the rapid advancement and success of Large Language Models (LLMs) have been a major talking point, particularly with their potential to outperform existing state-of-the-art technologies in various NLP tasks. Among these tasks, anonymization of unstructured, textual data represents a critical challenge, traditionally addressed by Named Entity Recognition (NER) models. This paper investigates the hype surrounding LLMs, specifically evaluating their effectiveness and applicability in the context of support ticket anonymization by conducting a comparative evaluation, pitting LLMs against an established support ticket anonymization solution that utilizes state-of-the-art transformer architectures for textual data anonymization. Our findings reveal significant limitations of LLMs in terms of overall performance and accuracy, particularly when facing real-world anonymization scenarios. © The Author(s), under exclusive license to Springer Nature Switzerland AG 2025.
A76: S075 | B76: Żarski T.L.; Janicki A. | C76: 2025 | D76: Enhancing Privacy While Preserving Context in Text Transformations by Large Language Models | E76: Information (Switzerland) | F76: Article | G76: 10.3390/info16010049 | H76: Núcleo | I76: N | J76: Anonimiza el texto con MITIE, spaCy, regex y LLM antes de usar herramientas en línea, con restitución posterior; cercano al proxy. | K76: Complementario | L76: Herramientas en línea | M76: LLM / asistentes | N76: No indicado | O76: No indicado o no aplica | P76: X | R76: X | T76: X | W76: =IF(AND(P76="X",OR(R76="X",S76="X",T76="X")),"Sí","No") -> Sí | AL76: Sí | AM76: Sí | AN76: No | AO76: No indicado | AP76: F1 0,829; contexto preservado en 93,23 % de los casos | AQ76: Abstract | AR76: Data security is a critical concern for Internet users, primarily as more people rely on social networks and online tools daily. Despite the convenience, many users are unaware of the risks posed to their sensitive and personal data. This study addresses this issue by presenting a comprehensive solution to prevent personal data leakage using online tools. We developed a conceptual solution that enhances user privacy by identifying and anonymizing named entity classes representing sensitive data while maintaining the original context by swapping source entities for functional data. Our approach utilizes natural language processing methods, combining machine learning tools such as MITIE and spaCy with rule-based text analysis. We employed regular expressions and large language models to anonymize text, preserving its context for further processing or enabling restoration to the original form after transformations. The results demonstrate the effectiveness of our custom-trained models, achieving an F1 score of 0.8292. Additionally, the proposed algorithms successfully preserved context in approximately 93.23% of test cases, indicating a promising solution for secure data handling in online environments. © 2025 by the authors.
A77: S076 | B77: Osborne J.D.; Trotter A.; O’Leary T.; Coffee C.; Cochran M.D.; Mansilla-Gonzalez L.; Nadimpalli A.; McAnnally A.; Almudaifer A.I.; Curtis J.R.; Aly S.M.; Kennedy R.E. | C77: 2025 | D77: A Markov Chain Replacement Strategy for Surrogate Identifiers: Minimizing Re-Identification Risk While Preserving Text Reuse | E77: Electronics (Switzerland) | F77: Article | G77: 10.3390/electronics14193945 | H77: Complementario | I77: C1 | J77: Estrategia de sustitución por sustitutos con cadenas de Markov; trata el reemplazo, no la detección. | K77: Complementario | L77: Clínico | M77: Salud / clínico | N77: Inglés | O77: Inglés | V77: X | W77: =IF(AND(P77="X",OR(R77="X",S77="X",T77="X")),"Sí","No") -> No | AL77: No | AM77: Sí | AN77: No | AO77: Corpus clínicos de dos instituciones | AP77: Fuga de PHI por documento de 27,1 % a 0,1 % | AQ77: Abstract | AR77: “Hiding in Plain Sight” (HIPS) strategies for Personal Health Information (PHI) replace PHI with surrogate values to hinder re-identification attempts. We evaluate three different HIPS strategies for PHI replacement, a standard Consistent replacement strategy, a Random replacement strategy, and a novel Markov model strategy. We evaluate the privacy-preserving benefits and relative utility for information extraction of these strategies on both a simulated PHI distribution and real clinical corpora from two different institutions using a range of false negative error rates (FNER). The Markov strategy consistently outperformed the Consistent and Random substitution strategies on both real data and in statistical simulations. Using FNER ranging from 0.1% to 5%, PHI leakage at the document level could be reduced from 27.1% to 0.1% and from 94.2% to 57.7% with the Markov strategy versus the standard Consistent substitution strategy, at 0.1% and 0.5% FNER, respectively. Additionally, we assessed the generated corpora containing synthetic PHI for reuse using a variety of information extraction methods. Results indicate that modern deep learning methods have similar performance on all strategies, but older machine learning techniques can suffer from the change in context. Overall, a Markov surrogate generation strategy substantially reduces the chance of inadvertent PHI release. © 2025 by the authors.
A78: S077 | B78: Chandrashekhar P.S.; Prakash J.S.; Laxman N.M.; Ismail S.A.; Prakash B.V.; Asabe J.P. | C78: 2025 | D78: RedactSafe: Ensuring PII Security in Legal Audits | E78: 2025 Global Conference in Emerging Technology, GINOTECH 2025 | F78: Conference paper | G78: 10.1109/GINOTECH63460.2025.11076720 | H78: Núcleo | I78: N | J78: Versión previa de RedactSafe (S070): reglas, ML y OCR con control de acceso. | K78: Núcleo | L78: Legal / auditoría | M78: Legal / policial | N78: No indicado | O78: No indicado o no aplica | P78: X | R78: X | V78: X | W78: =IF(AND(P78="X",OR(R78="X",S78="X",T78="X")),"Sí","No") -> Sí | AL78: No | AM78: No | AN78: No | AO78: Documentos estructurados y no estructurados | AP78: No reporta valores en el abstract | AQ78: Abstract | AR78: Currently, the management of PII, particularly when sharing and accessing documents on other platforms in this age of digital transformation, is important. In this paper, an integrated framework that attempts to detect and redact PII will be proposed using advanced NLP techniques, namely NER and OCR. These methods are synergistic in order to detect the sensitive data in the structure and unstructured documents. Our method brings together the combination of the conventional rule-based methods and the modern machine learning algorithms in order to dramatically improve the redaction process for both accuracy and flexibility. Regarding enhancing the security and integrity of the data, we apply blockchain, which applies the on-chain storage and verification processes with the strong feature of being immutable and traceable towards redacted documents. We thus establish an access control scheme as hybrid, combining ABAC and RBAC so that access rights of document access get maintained at a suitably secure level and abide to the standards of extant regulations. Experimentation shows results that this framework can function efficiently for data confidentiality preservation without disturbing the functionality in document sharing, which implies an integral approach for sensitive privacy environments. LATEX. © 2025 IEEE.
A79: S078 | B79: Jang S.; Cho Y.; Seong H.; Kim T.; Woo H. | C79: 2024 | D79: The Development of a Named Entity Recognizer for Detecting Personal Information Using a Korean Pretrained Language Model | E79: Applied Sciences (Switzerland) | F79: Article | G79: 10.3390/app14135682 | H79: Núcleo | I79: N | J79: Define un conjunto de etiquetas y una guía de anotación para PII en coreano; antecedente metodológico para lenguas distintas del inglés. | K79: Núcleo | L79: Conversacional / chatbots | M79: LLM / asistentes | N79: Coreano | O79: Otra lengua | S79: X | W79: =IF(AND(P79="X",OR(R79="X",S79="X",T79="X")),"Sí","No") -> No | AL79: No | AM79: No | AN79: No | AO79: Conjunto propio con 33 etiquetas de información personal | AP79: F1 0,943 | AQ79: Abstract | AR79: Social network services and chatbots are susceptible to personal information leakage while facilitating language learning without time or space constraints. Accurate detection of personal information is paramount in avoiding such leaks. Conventionally named entity recognizers commonly used for this purpose often fail owing to errors of unrecognition and misrecognition. Research in named entity recognition predominantly focuses on English, which poses challenges for non-English languages. By specifying procedures for the development of Korean-based tag sets, data collection, and preprocessing, we formulated directions on the application of entity recognition research to non-English languages. Such research could significantly benefit artificial intelligence (AI)-based natural language processing globally. We developed a personal information tag set comprising 33 items and established guidelines for dataset creation, later converting it into JSON format for AI learning. State-of-the-art AI models, BERT and ELECTRA, were employed to implement and evaluate the named entity recognition (NER) model, which achieved an 0.943 F1-score and outperformed conventional recognizers in detecting personal information. This advancement suggests that the proposed NER model can effectively prevent personal information leakage in systems processing interactive text data, marking a significant stride in safeguarding privacy across digital platforms. © 2024 by the authors.
A80: S079 | B80: Li J.; Yang L.; Peng L.; Zhang S.; Wang P.; Li Z.; Zhao H. | C80: 2024 | D80: Semantics-Preserved Distortion for Personal Privacy Protection in Information Management | E80: Lecture Notes in Computer Science (including subseries Lecture Notes in Artificial Intelligence and Lecture Notes in Bioinformatics) | F80: Conference paper | G80: 10.1007/978-3-031-72344-5_26 | H80: Complementario | I80: C1 | J80: Distorsiona el texto preservando la semántica para evitar memorización; no detecta entidades sensibles. | K80: Complementario | L80: General | M80: General / documentos | N80: Inglés | O80: Inglés | V80: X | W80: =IF(AND(P80="X",OR(R80="X",S80="X",T80="X")),"Sí","No") -> No | AL80: No | AM80: Sí | AN80: No | AO80: Tareas de NER, análisis sintáctico y comprensión lectora | AP80: Divergencia de distribución vecina | AQ80: Abstract | AR80: In recent years, machine learning—particularly deep learning—has significantly impacted the field of information management. While several strategies have been proposed to restrict models from learning and memorizing sensitive information from raw texts, this paper suggests a more linguistically-grounded approach to distort texts while maintaining semantic integrity. To this end, we leverage Neighboring Distribution Divergence, a novel metric to assess the preservation of semantic meaning during distortion. Building on this metric, we present two distinct frameworks for semantic-preserving distortion: a generative approach and a substitutive approach. Our evaluations across various tasks, including named entity recognition, constituency parsing, and machine reading comprehension, affirm the plausibility and efficacy of our distortion technique in personal privacy protection. We also test our method against attribute attacks in three privacy-focused assignments within the NLP domain, and the findings underscore the simplicity and efficacy of our data-based improvement approach over structural improvement approaches. Moreover, we explore privacy protection in a specific medical information management scenario, showing our method effectively limits sensitive data memorization, underscoring its practicality. © The Author(s), under exclusive license to Springer Nature Switzerland AG 2024.
A81: S080 | B81: Psarra E.; Stefanidis K. | C81: 2026 | D81: On the Applicability of LLMs and SLMs for Privacy-Preserving Named Entity Recognition in Financial Applications | E81: Applied Sciences (Switzerland) | F81: Article | G81: 10.3390/app16073332 | H81: Núcleo | I81: N | J81: Compara 15 modelos tipo BERT para PII financiera; los modelos pequeños compiten con los grandes. | K81: Núcleo | L81: Financiero | M81: Financiero | N81: Inglés | O81: Inglés | S81: X | W81: =IF(AND(P81="X",OR(R81="X",S81="X",T81="X")),"Sí","No") -> No | AL81: No | AM81: No | AN81: No | AO81: AI4Privacy PII 43K | AP81: Exactitud, P, R y F1 | AQ81: Abstract | AR81: This work explores how deep learning models, with different numbers of parameters, can be effectively applied to detect personal data within unstructured text using Named Entity Recognition (NER) techniques. We evaluate the performance of various architectures by leveraging a plethora of language models (LMs) consisting of Distilbert-base-uncased, Distilbert-base-cased, Bert-base-uncased, Bert-base-cased, Bert-large-uncased, Bert-large-cased, ModernBERT-base, ModernBERT-large, nomic-BERT-2048, RoBERTa-base, DistilRoBERTa-base, RoBERTa-large, Deberta-v3-xsmall, Deberta-v3-small, and Deberta-v3-base, which are evaluated using the performance indices of accuracy, precision, recall, and F1-score. Our experiments show that some Small Language Models (SLMs) compete equally with some corresponding LLMs (Large Language Models), based on the specific PII (Personally Identifiable Information) dataset, thus enhancing personal data detection, which is of paramount importance in financial applications. Moreover, we proposed a novel architecture based on an optimized transformer fine-tuning strategy to improve PII recognition across diverse contexts and conducted an extensive comparative analysis to evaluate the performance of our proposed architecture in relation to all relevant existing approaches reported in the literature. This evaluation, performed on the AI4Privacy PII 43 K dataset, encompasses every publicly available work we identified and provides a thorough benchmarking of our methods within the current research field. The results highlight both the strengths and limitations of existing solutions and demonstrate the effectiveness of SLMs in addressing the challenges of privacy-preserving information extraction. © 2026 by the authors.
A82: S081 | B82: Schiezaro M.; Rosa G.; Campos B.A.G.; Pedrini H. | C82: 2026 | D82: Guardians of the data: NER and LLMs for effective medical record anonymization in Brazilian Portuguese | E82: Frontiers in Public Health | F82: Article | G82: 10.3389/fpubh.2025.1717303 | H82: Núcleo | I82: N | J82: Compara NER con BERT y reescritura generativa con T5 y GPT; los datos sintéticos mejoran la generalización. | K82: Núcleo | L82: Clínico | M82: Salud / clínico | N82: Portugués (Brasil) | O82: Otra lengua | S82: X | T82: X | W82: =IF(AND(P82="X",OR(R82="X",S82="X",T82="X")),"Sí","No") -> No | X82: X | AB82: X | AD82: X | AE82: X | AL82: No | AM82: Sí | AN82: No | AO82: AnonyMed-BR, con registros reales y sintéticos | AP82: F1 > 0,90 | AQ82: Abstract y texto completo | AR82: Introduction: The anonymization of medical records is essential to protect patient privacy while enabling the use of clinical data for research and Natural Language Processing (NLP) applications. However, for Brazilian Portuguese, the lack of publicly available and high-quality anonymized datasets limits progress in this area. Methods: In this study, we present AnonyMed-BR, a novel dataset of Brazilian medical records that includes both real and synthetic samples, manually annotated to identify personally identifiable information (PII) such as names, dates, locations, and healthcare identifiers. To benchmark our dataset and assess anonymization performance, we evaluate two anonymization strategies: (i) an extractive strategy based on Named Entity Recognition (NER) using BERT-based models, and (ii) a generative strategy using T5-based and GPT-based models to rewrite texts while masking sensitive entities. We conduct a comprehensive series of experiments to evaluate and compare anonymization strategies. Specifically, we assess the impact of incorporating synthetic generated records on model performance by contrasting models fine-tuned solely on real data with those fine-tuned on synthetic samples. We also investigate whether pre-training on biomedical corpora or task-specific fine-tuning more effectively improves performance in the anonymization task. Finally, to support robust evaluation, we introduce an LLM-as-a-Judge framework that leverages a reasoning Large Language Model (LLM) to score anonymization quality, estimate information loss, and assess reidentification risk. Model performance was primarily evaluated using the F1 score on a held-out test set. Results: All evaluated models achieved good performance in the anonymization task, with the best models reaching F1 scores above 0.90. Both extractive and generative approaches were effective in identifying and masking sensitive entities while preserving the clinical meaning of the texts. Experiments also revealed that including synthetic data improved model generalization, and that task-specific fine-tuning yielded greater performance gains than pre-training the model on biomedical domain. Discussion and conclusion: To the best of our knowledge, AnonyMed-BR is the first manually annotated anonymization dataset for Brazilian Portuguese medical texts, enabling systematic evaluation of both extractive and generative models. The dataset and methodology establish a foundation for privacy-preserving NLP research in the Brazilian healthcare context and the good performance achieved by all models demonstrates the feasibility of developing reliable anonymization systems for Brazilian clinical data. Importantly, the ability to anonymize sensitive information opens opportunities to create new datasets and train models for a variety of downstream tasks in the medical domain, such as clinical outcome prediction, medical entity recognition, diagnostic support, and patient stratification, fostering the growth of NLP research for Brazilian Portuguese healthcare texts. Motivated by our findings, future work includes a deeper exploration of synthetic data generation and utilization. Additionally, we plan to evaluate the models across different languages and textual domains, and to expand the dataset to cover these new languages and domains. These efforts aim to develop more complex anonymization systems with higher generalization capability, ultimately enabling broader applications and safer sharing of data in diverse research and operational settings. All resources are publicly available at https://github.com/venturusbr/AnonyMED-BR. Copyright © 2026 Schiezaro, Rosa, Campos and Pedrini.
A83: S082 | B83: Sharma B.M.; Malik A. | C83: 2025 | D83: Automated Threat Attack Categorisation into Cloud Service Models | E83: Procedia Computer Science | F83: Conference paper | G83: 10.1016/j.procs.2025.04.144 | H83: Excluido | I83: E2 | J83: Clasifica ataques en servicios de nube; el NER no se usa para información sensible. | K83: Excluido | L83: Ciberseguridad / nube | M83: Ciberseguridad u otro problema | N83: No aplica | O83: No indicado o no aplica | R83: X | W83: =IF(AND(P83="X",OR(R83="X",S83="X",T83="X")),"Sí","No") -> No | AL83: No | AM83: No | AN83: No | AO83: - | AP83: Exactitud 85 % | AQ83: Abstract | AR83: In today's interconnected world, our heavy reliance on cloud-based services for daily tasks raises concerns about the security and privacy of our personal information. Cloud services have become an integral part of our lives, offering convenience and accessibility. However, the shared responsibility model and diverse service architectures of cloud computing necessitate different approaches to security assessment and penetration testing. This paper presents a comprehensive model-based approach that focuses on all three service models of the cloud. by adopting a system and model-based perspective, the study emphasizes on a shared approach to security. The methodology incorporates both white hat and grey hat techniques, which thoroughly test the security of cloud systems, ensuring a robust defense against various potential attacks. In addition to this, we are also present a novel approach for categorization using a combination of Long Short-Term Memory (LSTM) and Word2Vec, with a focus on Named Entity Recognition (NER). This approach achieves an impressive accuracy of 85 percent, which indicates its effectiveness in accurately identifying and categorizing named entities within the text data. The findings contribute in improving the overall security posture of cloud services, providing users with the confidence that their data is well protected. © 2025 The Author(s). Published by Elsevier B.V.
